[{"closedPRs":2697,"closedIssues":11656,"mergedPRs":13958,"openPRs":226,"stars":48912,"timestamp":1612616348,"openIssues":363},{"stars":48912,"closedIssues":11656,"openPRs":225,"mergedPRs":13958,"closedPRs":2697,"openIssues":363,"timestamp":1612612115},{"openPRs":222,"closedIssues":11656,"closedPRs":2697,"timestamp":1612608660,"mergedPRs":13958,"stars":48911,"openIssues":363},{"openPRs":222,"closedPRs":2697,"stars":48912,"openIssues":363,"timestamp":1612605126,"closedIssues":11656,"mergedPRs":13958},{"stars":48911,"openPRs":223,"openIssues":363,"closedPRs":2697,"mergedPRs":13957,"timestamp":1612601634,"closedIssues":11656},{"closedIssues":11654,"openIssues":365,"openPRs":223,"stars":48910,"timestamp":1612597718,"mergedPRs":13957,"closedPRs":2697},{"stars":48910,"closedPRs":2697,"mergedPRs":13957,"closedIssues":11654,"openPRs":223,"openIssues":365,"timestamp":1612594484},{"stars":48910,"mergedPRs":13957,"openIssues":365,"closedPRs":2697,"timestamp":1612590506,"openPRs":223,"closedIssues":11654},{"closedIssues":11654,"openIssues":365,"stars":48910,"openPRs":223,"mergedPRs":13957,"timestamp":1612587309,"closedPRs":2697},{"closedIssues":11654,"closedPRs":2697,"openIssues":364,"stars":48910,"openPRs":223,"timestamp":1612583541,"mergedPRs":13957},{"timestamp":1612579844,"mergedPRs":13957,"openPRs":223,"closedIssues":11654,"stars":48910,"closedPRs":2697,"openIssues":363},{"stars":48910,"closedIssues":11654,"timestamp":1612576975,"mergedPRs":13957,"closedPRs":2697,"openIssues":363,"openPRs":223},{"closedIssues":11654,"closedPRs":2697,"mergedPRs":13957,"openPRs":223,"timestamp":1612574552,"stars":48910,"openIssues":363},{"openIssues":364,"timestamp":1612569104,"closedIssues":11653,"openPRs":222,"mergedPRs":13957,"stars":48908,"closedPRs":2697},{"stars":48906,"closedIssues":11653,"mergedPRs":13957,"timestamp":1612565591,"openPRs":222,"openIssues":363,"closedPRs":2697},{"closedIssues":11653,"stars":48904,"openIssues":363,"timestamp":1612561767,"closedPRs":2697,"mergedPRs":13957,"openPRs":222},{"closedPRs":2697,"openIssues":363,"closedIssues":11653,"openPRs":222,"timestamp":1612558112,"stars":48903,"mergedPRs":13957},{"openPRs":221,"mergedPRs":13957,"stars":48902,"closedPRs":2697,"closedIssues":11653,"timestamp":1612554506,"openIssues":363},{"openIssues":363,"stars":48903,"openPRs":222,"mergedPRs":13956,"closedPRs":2697,"timestamp":1612551411,"closedIssues":11653},{"mergedPRs":13955,"openIssues":362,"closedIssues":11653,"closedPRs":2697,"openPRs":222,"stars":48902,"timestamp":1612547598},{"mergedPRs":13954,"closedPRs":2697,"closedIssues":11652,"openPRs":221,"openIssues":363,"timestamp":1612545172,"stars":48902},{"mergedPRs":13952,"closedIssues":11652,"timestamp":1612540357,"openIssues":363,"stars":48901,"openPRs":221,"closedPRs":2697},{"timestamp":1612536496,"openPRs":221,"closedIssues":11652,"mergedPRs":13952,"openIssues":363,"closedPRs":2697,"stars":48902},{"timestamp":1612532912,"stars":48900,"closedPRs":2697,"mergedPRs":13952,"openIssues":365,"closedIssues":11649,"openPRs":220},{"openPRs":220,"openIssues":365,"closedPRs":2697,"closedIssues":11649,"mergedPRs":13952,"timestamp":1612529967,"stars":48901},{"closedIssues":11649,"mergedPRs":13952,"stars":48900,"openIssues":365,"closedPRs":2696,"timestamp":1612525696,"openPRs":220},{"timestamp":1612522245,"stars":48901,"openIssues":365,"openPRs":221,"closedPRs":2696,"mergedPRs":13951,"closedIssues":11649},{"openPRs":221,"closedPRs":2696,"mergedPRs":13951,"timestamp":1612518733,"stars":48899,"openIssues":365,"closedIssues":11649},{"openPRs":221,"openIssues":364,"mergedPRs":13951,"timestamp":1612515256,"closedPRs":2696,"closedIssues":11650,"stars":48899},{"timestamp":1612511290,"openPRs":221,"closedPRs":2696,"stars":48898,"closedIssues":11647,"openIssues":366,"mergedPRs":13951},{"openPRs":221,"mergedPRs":13951,"stars":48897,"timestamp":1612508088,"closedIssues":11647,"closedPRs":2696,"openIssues":366},{"closedIssues":11647,"closedPRs":2696,"mergedPRs":13951,"openIssues":366,"openPRs":221,"timestamp":1612504091,"stars":48896},{"openPRs":221,"stars":48896,"closedPRs":2696,"openIssues":366,"timestamp":1612500907,"closedIssues":11647,"mergedPRs":13951},{"closedIssues":11647,"stars":48896,"timestamp":1612497125,"closedPRs":2696,"mergedPRs":13951,"openPRs":221,"openIssues":366},{"mergedPRs":13951,"closedPRs":2696,"timestamp":1612493498,"closedIssues":11646,"openIssues":367,"openPRs":221,"stars":48897},{"stars":48897,"openPRs":221,"closedIssues":11646,"timestamp":1612490669,"mergedPRs":13951,"closedPRs":2696,"openIssues":367},{"closedPRs":2696,"closedIssues":11645,"openPRs":221,"timestamp":1612488221,"stars":48896,"mergedPRs":13951,"openIssues":368},{"closedPRs":2696,"closedIssues":11645,"timestamp":1612482720,"openPRs":221,"mergedPRs":13951,"stars":48893,"openIssues":368},{"openPRs":221,"closedPRs":2696,"stars":48892,"mergedPRs":13951,"closedIssues":11645,"timestamp":1612479223,"openIssues":368},{"closedPRs":2696,"openIssues":366,"openPRs":221,"timestamp":1612475365,"closedIssues":11646,"mergedPRs":13951,"stars":48891},{"closedPRs":2696,"stars":48889,"openPRs":221,"mergedPRs":13951,"timestamp":1612471721,"closedIssues":11646,"openIssues":366},{"openIssues":365,"closedPRs":2696,"openPRs":221,"closedIssues":11646,"mergedPRs":13951,"stars":48889,"timestamp":1612468115},{"closedPRs":2696,"stars":48888,"closedIssues":11646,"timestamp":1612464922,"mergedPRs":13951,"openPRs":221,"openIssues":365},{"openIssues":364,"stars":48888,"timestamp":1612461185,"closedPRs":2696,"mergedPRs":13951,"closedIssues":11646,"openPRs":221},{"openIssues":364,"closedPRs":2696,"openPRs":221,"closedIssues":11646,"mergedPRs":13951,"timestamp":1612458651,"stars":48887},{"openPRs":220,"mergedPRs":13951,"openIssues":364,"timestamp":1612453979,"closedIssues":11646,"closedPRs":2696,"stars":48887},{"closedPRs":2696,"closedIssues":11646,"openPRs":220,"mergedPRs":13951,"timestamp":1612450104,"openIssues":364,"stars":48886},{"openIssues":364,"openPRs":220,"mergedPRs":13951,"timestamp":1612446501,"closedIssues":11646,"closedPRs":2696,"stars":48886},{"stars":48886,"closedIssues":11646,"closedPRs":2696,"openPRs":221,"timestamp":1612443613,"mergedPRs":13950,"openIssues":364},{"stars":48885,"timestamp":1612439958,"closedIssues":11646,"mergedPRs":13950,"closedPRs":2696,"openPRs":221,"openIssues":364},{"closedPRs":2695,"timestamp":1612435887,"openIssues":364,"stars":48883,"openPRs":222,"closedIssues":11646,"mergedPRs":13949},{"stars":48883,"timestamp":1612432332,"mergedPRs":13947,"openPRs":223,"closedIssues":11644,"closedPRs":2695,"openIssues":366},{"closedIssues":11644,"closedPRs":2695,"timestamp":1612428867,"openPRs":222,"mergedPRs":13946,"stars":48882,"openIssues":366},{"stars":48882,"mergedPRs":13946,"openIssues":366,"openPRs":222,"closedIssues":11644,"closedPRs":2695,"timestamp":1612424888},{"timestamp":1612421716,"stars":48882,"mergedPRs":13946,"openPRs":222,"openIssues":366,"closedIssues":11644,"closedPRs":2695},{"closedPRs":2695,"closedIssues":11644,"timestamp":1612417693,"stars":48882,"openIssues":366,"openPRs":222,"mergedPRs":13946},{"mergedPRs":13946,"closedIssues":11644,"openIssues":366,"closedPRs":2695,"openPRs":222,"timestamp":1612414553,"stars":48882},{"timestamp":1612410713,"closedIssues":11643,"mergedPRs":13946,"openPRs":222,"openIssues":367,"closedPRs":2695,"stars":48881},{"timestamp":1612407215,"stars":48881,"openPRs":222,"mergedPRs":13946,"closedIssues":11643,"closedPRs":2695,"openIssues":367},{"openPRs":222,"stars":48881,"timestamp":1612404278,"closedIssues":11643,"closedPRs":2695,"openIssues":366,"mergedPRs":13946},{"openPRs":222,"stars":48881,"closedPRs":2695,"openIssues":365,"timestamp":1612401800,"mergedPRs":13946,"closedIssues":11643},{"stars":48882,"timestamp":1612396365,"closedPRs":2695,"closedIssues":11643,"openIssues":365,"openPRs":223,"mergedPRs":13945},{"openIssues":365,"timestamp":1612392818,"closedIssues":11643,"mergedPRs":13945,"closedPRs":2695,"stars":48882,"openPRs":223},{"closedPRs":2695,"openPRs":223,"openIssues":365,"timestamp":1612389051,"closedIssues":11643,"stars":48882,"mergedPRs":13945},{"openPRs":223,"closedPRs":2695,"mergedPRs":13945,"stars":48882,"openIssues":365,"closedIssues":11643,"timestamp":1612385570},{"stars":48882,"mergedPRs":13944,"closedIssues":11640,"closedPRs":2694,"openPRs":225,"openIssues":368,"timestamp":1612381842},{"openPRs":225,"closedIssues":11640,"stars":48881,"closedPRs":2694,"openIssues":368,"timestamp":1612379066,"mergedPRs":13944},{"mergedPRs":13944,"openPRs":225,"closedPRs":2694,"timestamp":1612375493,"closedIssues":11640,"stars":48880,"openIssues":368},{"mergedPRs":13944,"closedIssues":11640,"timestamp":1612372956,"stars":48880,"openPRs":225,"openIssues":368,"closedPRs":2694},{"closedIssues":11640,"openPRs":227,"closedPRs":2693,"stars":48880,"mergedPRs":13943,"openIssues":368,"timestamp":1612367865},{"openIssues":368,"closedPRs":2693,"mergedPRs":13943,"closedIssues":11640,"timestamp":1612364230,"openPRs":226,"stars":48880},{"openPRs":226,"closedPRs":2693,"timestamp":1612360423,"openIssues":368,"closedIssues":11640,"mergedPRs":13943,"stars":48880},{"timestamp":1612357599,"openPRs":226,"mergedPRs":13943,"closedIssues":11640,"closedPRs":2693,"stars":48880,"openIssues":368},{"openIssues":367,"stars":48879,"closedPRs":2693,"closedIssues":11640,"mergedPRs":13943,"timestamp":1612353044,"openPRs":224},{"closedIssues":11640,"stars":48879,"openPRs":224,"openIssues":366,"mergedPRs":13943,"closedPRs":2693,"timestamp":1612349763},{"stars":48877,"closedPRs":2693,"closedIssues":11637,"openIssues":369,"timestamp":1612346219,"openPRs":223,"mergedPRs":13943},{"openIssues":368,"openPRs":224,"timestamp":1612342752,"closedPRs":2693,"stars":48874,"mergedPRs":13942,"closedIssues":11637},{"closedPRs":2693,"stars":48873,"mergedPRs":13942,"openPRs":223,"closedIssues":11637,"openIssues":368,"timestamp":1612338709},{"openPRs":223,"timestamp":1612335600,"stars":48871,"openIssues":368,"closedPRs":2693,"closedIssues":11637,"mergedPRs":13942},{"openPRs":223,"closedIssues":11637,"stars":48871,"closedPRs":2693,"openIssues":367,"timestamp":1612331498,"mergedPRs":13942},{"openIssues":367,"mergedPRs":13942,"closedIssues":11637,"timestamp":1612328425,"openPRs":223,"closedPRs":2693,"stars":48870},{"stars":48869,"closedIssues":11637,"timestamp":1612324662,"closedPRs":2693,"mergedPRs":13942,"openPRs":223,"openIssues":367},{"openPRs":223,"timestamp":1612321218,"closedIssues":11637,"closedPRs":2693,"mergedPRs":13942,"openIssues":367,"stars":48867},{"openIssues":367,"mergedPRs":13942,"timestamp":1612318588,"openPRs":223,"closedPRs":2693,"closedIssues":11637,"stars":48867},{"timestamp":1612315851,"openIssues":367,"closedIssues":11637,"mergedPRs":13942,"openPRs":223,"closedPRs":2693,"stars":48867},{"mergedPRs":13941,"stars":48866,"closedIssues":11635,"openIssues":369,"closedPRs":2693,"timestamp":1612310122,"openPRs":223},{"openPRs":222,"closedPRs":2693,"mergedPRs":13941,"closedIssues":11635,"timestamp":1612306668,"openIssues":369,"stars":48866},{"closedIssues":11635,"closedPRs":2693,"timestamp":1612302865,"openPRs":222,"stars":48866,"mergedPRs":13941,"openIssues":369},{"timestamp":1612299172,"closedPRs":2693,"openIssues":369,"closedIssues":11635,"stars":48866,"mergedPRs":13941,"openPRs":222},{"closedPRs":2693,"mergedPRs":13941,"timestamp":1612295556,"openPRs":221,"closedIssues":11635,"openIssues":369,"stars":48863},{"closedIssues":11635,"closedPRs":2693,"openIssues":368,"timestamp":1612292877,"mergedPRs":13941,"openPRs":221,"stars":48862},{"openIssues":367,"closedIssues":11635,"openPRs":221,"stars":48862,"timestamp":1612289678,"mergedPRs":13941,"closedPRs":2693},{"closedIssues":11635,"mergedPRs":13940,"openPRs":221,"closedPRs":2693,"stars":48862,"openIssues":366,"timestamp":1612287040},{"closedIssues":11635,"mergedPRs":13939,"stars":48860,"openIssues":366,"timestamp":1612281664,"openPRs":222,"closedPRs":2693},{"closedPRs":2693,"openPRs":223,"mergedPRs":13937,"stars":48859,"timestamp":1612277799,"closedIssues":11635,"openIssues":366},{"closedPRs":2693,"stars":48859,"timestamp":1612274128,"openPRs":223,"closedIssues":11635,"openIssues":366,"mergedPRs":13937},{"timestamp":1612271475,"openPRs":224,"mergedPRs":13935,"openIssues":366,"stars":48858,"closedIssues":11635,"closedPRs":2693},{"timestamp":1612266842,"stars":48858,"mergedPRs":13935,"openIssues":366,"closedIssues":11635,"openPRs":222,"closedPRs":2693},{"mergedPRs":13935,"closedPRs":2693,"openPRs":222,"stars":48857,"timestamp":1612263608,"openIssues":366,"closedIssues":11635},{"timestamp":1612260124,"openPRs":223,"openIssues":366,"closedIssues":11635,"stars":48855,"mergedPRs":13934,"closedPRs":2693},{"mergedPRs":13934,"closedIssues":11634,"closedPRs":2693,"stars":48854,"openPRs":223,"timestamp":1612256546,"openIssues":367},{"mergedPRs":13934,"openPRs":223,"closedIssues":11634,"closedPRs":2693,"openIssues":367,"timestamp":1612252592,"stars":48853},{"stars":48852,"closedPRs":2693,"timestamp":1612249423,"closedIssues":11634,"mergedPRs":13934,"openPRs":223,"openIssues":367},{"timestamp":1612245403,"openPRs":223,"stars":48849,"closedIssues":11634,"closedPRs":2693,"mergedPRs":13934,"openIssues":367},{"openIssues":367,"closedIssues":11634,"closedPRs":2693,"openPRs":223,"mergedPRs":13934,"stars":48849,"timestamp":1612242295},{"timestamp":1612238578,"openPRs":223,"openIssues":367,"closedPRs":2693,"closedIssues":11634,"stars":48849,"mergedPRs":13934},{"closedPRs":2693,"mergedPRs":13934,"stars":48848,"closedIssues":11634,"openIssues":367,"openPRs":223,"timestamp":1612235102},{"openPRs":223,"stars":48848,"openIssues":367,"mergedPRs":13934,"closedPRs":2693,"closedIssues":11634,"timestamp":1612232492},{"timestamp":1612229959,"openIssues":367,"closedIssues":11634,"stars":48846,"mergedPRs":13934,"openPRs":223,"closedPRs":2693},{"closedPRs":2693,"closedIssues":11634,"stars":48846,"timestamp":1612224086,"openPRs":224,"mergedPRs":13933,"openIssues":367},{"stars":48845,"closedIssues":11634,"timestamp":1612220506,"closedPRs":2693,"openPRs":224,"mergedPRs":13933,"openIssues":367},{"timestamp":1612216565,"mergedPRs":13933,"openPRs":224,"closedIssues":11634,"closedPRs":2693,"openIssues":367,"stars":48845},{"openPRs":224,"stars":48845,"timestamp":1612213015,"mergedPRs":13933,"closedIssues":11634,"closedPRs":2693,"openIssues":367},{"mergedPRs":13933,"openIssues":367,"stars":48845,"closedIssues":11634,"closedPRs":2693,"openPRs":223,"timestamp":1612209370},{"closedIssues":11634,"closedPRs":2693,"mergedPRs":13933,"openPRs":223,"openIssues":367,"timestamp":1612206701,"stars":48845},{"openIssues":367,"mergedPRs":13933,"openPRs":223,"timestamp":1612203277,"stars":48844,"closedIssues":11634,"closedPRs":2693},{"closedPRs":2693,"openPRs":223,"timestamp":1612200615,"mergedPRs":13933,"openIssues":367,"closedIssues":11634,"stars":48842},{"closedIssues":11633,"closedPRs":2693,"mergedPRs":13933,"stars":48841,"openPRs":222,"openIssues":367,"timestamp":1612195269},{"closedIssues":11633,"closedPRs":2693,"stars":48840,"openIssues":367,"mergedPRs":13933,"openPRs":222,"timestamp":1612191373},{"stars":48839,"timestamp":1612187724,"openIssues":367,"closedPRs":2693,"openPRs":221,"closedIssues":11633,"mergedPRs":13933},{"mergedPRs":13933,"stars":48839,"closedIssues":11633,"timestamp":1612185084,"openIssues":367,"openPRs":221,"closedPRs":2693},{"openIssues":367,"closedIssues":11633,"mergedPRs":13932,"timestamp":1612180434,"stars":48837,"closedPRs":2693,"openPRs":222},{"timestamp":1612177208,"openIssues":367,"closedIssues":11633,"stars":48837,"openPRs":222,"mergedPRs":13932,"closedPRs":2693},{"timestamp":1612173745,"openPRs":221,"closedIssues":11633,"openIssues":367,"mergedPRs":13932,"closedPRs":2693,"stars":48836},{"timestamp":1612170160,"openIssues":367,"closedPRs":2693,"mergedPRs":13930,"stars":48836,"closedIssues":11633,"openPRs":222},{"timestamp":1612166188,"stars":48835,"openIssues":370,"mergedPRs":13930,"closedIssues":11630,"closedPRs":2692,"openPRs":223},{"openPRs":222,"timestamp":1612163036,"stars":48834,"openIssues":370,"mergedPRs":13930,"closedIssues":11630,"closedPRs":2692},{"closedPRs":2692,"stars":48834,"openIssues":370,"openPRs":222,"mergedPRs":13930,"closedIssues":11630,"timestamp":1612159024},{"openPRs":222,"closedIssues":11630,"mergedPRs":13930,"stars":48834,"openIssues":370,"timestamp":1612155943,"closedPRs":2692},{"openIssues":369,"stars":48833,"timestamp":1612152162,"closedIssues":11630,"mergedPRs":13930,"closedPRs":2692,"openPRs":221},{"openIssues":369,"closedPRs":2692,"stars":48833,"timestamp":1612148744,"closedIssues":11630,"mergedPRs":13930,"openPRs":218},{"openPRs":216,"closedPRs":2692,"mergedPRs":13930,"stars":48833,"openIssues":369,"timestamp":1612146118,"closedIssues":11630},{"closedIssues":11630,"mergedPRs":13930,"timestamp":1612143879,"stars":48833,"openIssues":369,"closedPRs":2692,"openPRs":215},{"timestamp":1612138011,"closedIssues":11628,"closedPRs":2692,"stars":48833,"mergedPRs":13930,"openIssues":371,"openPRs":214},{"mergedPRs":13930,"timestamp":1612134044,"closedIssues":11628,"stars":48832,"openIssues":371,"openPRs":214,"closedPRs":2692},{"closedPRs":2692,"mergedPRs":13930,"openIssues":371,"closedIssues":11628,"timestamp":1612130219,"stars":48831,"openPRs":214},{"closedPRs":2692,"mergedPRs":13930,"openPRs":214,"closedIssues":11628,"openIssues":371,"timestamp":1612126644,"stars":48831},{"openIssues":371,"openPRs":214,"mergedPRs":13930,"stars":48830,"timestamp":1612122933,"closedPRs":2692,"closedIssues":11628},{"timestamp":1612120152,"stars":48830,"openIssues":370,"openPRs":214,"closedPRs":2692,"closedIssues":11628,"mergedPRs":13930},{"openIssues":370,"openPRs":214,"stars":48830,"closedIssues":11628,"timestamp":1612116739,"mergedPRs":13930,"closedPRs":2692},{"closedPRs":2692,"timestamp":1612114104,"stars":48831,"closedIssues":11628,"openIssues":370,"openPRs":214,"mergedPRs":13930},{"timestamp":1612108858,"closedPRs":2692,"closedIssues":11628,"stars":48831,"mergedPRs":13930,"openPRs":214,"openIssues":370},{"stars":48830,"closedPRs":2692,"closedIssues":11628,"mergedPRs":13930,"openIssues":370,"openPRs":214,"timestamp":1612104912},{"timestamp":1612101301,"openPRs":214,"mergedPRs":13930,"closedIssues":11628,"stars":48830,"openIssues":370,"closedPRs":2692},{"openIssues":370,"closedPRs":2692,"openPRs":214,"timestamp":1612098591,"stars":48830,"mergedPRs":13930,"closedIssues":11628},{"stars":48829,"closedPRs":2692,"closedIssues":11627,"openIssues":371,"openPRs":214,"timestamp":1612093983,"mergedPRs":13930},{"mergedPRs":13930,"openPRs":214,"stars":48827,"timestamp":1612090742,"closedIssues":11627,"closedPRs":2692,"openIssues":371},{"closedPRs":2692,"closedIssues":11627,"mergedPRs":13930,"openPRs":214,"stars":48827,"timestamp":1612087263,"openIssues":371},{"timestamp":1612083707,"stars":48827,"closedPRs":2692,"mergedPRs":13930,"openIssues":371,"closedIssues":11627,"openPRs":214},{"mergedPRs":13930,"closedPRs":2692,"timestamp":1612079733,"openPRs":214,"closedIssues":11627,"openIssues":371,"stars":48826},{"stars":48826,"openIssues":371,"closedPRs":2692,"mergedPRs":13930,"timestamp":1612076584,"closedIssues":11627,"openPRs":214},{"timestamp":1612072563,"stars":48825,"openPRs":214,"closedPRs":2692,"openIssues":371,"closedIssues":11627,"mergedPRs":13930},{"openIssues":371,"mergedPRs":13930,"stars":48825,"timestamp":1612069528,"openPRs":214,"closedIssues":11627,"closedPRs":2692},{"closedPRs":2692,"stars":48825,"timestamp":1612065731,"closedIssues":11627,"openIssues":369,"mergedPRs":13930,"openPRs":214},{"timestamp":1612062273,"openPRs":214,"closedPRs":2692,"mergedPRs":13930,"openIssues":369,"stars":48823,"closedIssues":11627},{"closedPRs":2692,"openIssues":369,"stars":48823,"closedIssues":11627,"mergedPRs":13930,"timestamp":1612059687,"openPRs":214},{"openPRs":214,"stars":48823,"closedPRs":2692,"closedIssues":11627,"openIssues":369,"mergedPRs":13930,"timestamp":1612057443},{"openPRs":214,"closedPRs":2692,"timestamp":1612051178,"closedIssues":11624,"mergedPRs":13930,"stars":48823,"openIssues":369},{"openPRs":214,"mergedPRs":13930,"closedIssues":11624,"timestamp":1612047619,"stars":48822,"closedPRs":2692,"openIssues":369},{"mergedPRs":13930,"timestamp":1612043809,"closedIssues":11624,"openIssues":369,"stars":48824,"openPRs":214,"closedPRs":2692},{"openIssues":369,"closedPRs":2692,"stars":48825,"openPRs":214,"closedIssues":11624,"mergedPRs":13930,"timestamp":1612040132},{"mergedPRs":13930,"openPRs":214,"closedIssues":11624,"stars":48825,"timestamp":1612036507,"openIssues":369,"closedPRs":2692},{"openPRs":214,"timestamp":1612033747,"closedIssues":11624,"closedPRs":2692,"mergedPRs":13930,"openIssues":369,"stars":48825},{"timestamp":1612030317,"openPRs":214,"mergedPRs":13930,"stars":48825,"closedIssues":11624,"closedPRs":2692,"openIssues":369},{"closedPRs":2692,"stars":48825,"mergedPRs":13930,"openPRs":214,"openIssues":369,"timestamp":1612027686,"closedIssues":11624},{"timestamp":1612022446,"mergedPRs":13930,"openIssues":369,"openPRs":214,"closedIssues":11624,"stars":48823,"closedPRs":2692},{"timestamp":1612018529,"stars":48824,"closedPRs":2692,"closedIssues":11624,"openIssues":369,"openPRs":214,"mergedPRs":13930},{"timestamp":1612014914,"mergedPRs":13930,"openPRs":214,"closedPRs":2692,"stars":48824,"closedIssues":11624,"openIssues":369},{"stars":48823,"mergedPRs":13930,"timestamp":1612012177,"openPRs":214,"openIssues":369,"closedIssues":11624,"closedPRs":2692},{"mergedPRs":13930,"openPRs":214,"stars":48823,"openIssues":369,"closedPRs":2692,"closedIssues":11624,"timestamp":1612007610},{"openPRs":214,"timestamp":1612004363,"stars":48823,"closedIssues":11624,"closedPRs":2692,"mergedPRs":13930,"openIssues":369},{"stars":48823,"mergedPRs":13930,"openIssues":368,"closedPRs":2692,"openPRs":214,"closedIssues":11624,"timestamp":1612000858},{"stars":48823,"timestamp":1611997300,"closedIssues":11624,"mergedPRs":13930,"openPRs":214,"openIssues":368,"closedPRs":2692},{"timestamp":1611993349,"closedPRs":2692,"mergedPRs":13930,"openIssues":368,"stars":48823,"closedIssues":11624,"openPRs":214},{"closedIssues":11624,"openIssues":368,"openPRs":214,"closedPRs":2692,"mergedPRs":13930,"timestamp":1611990185,"stars":48823},{"stars":48823,"timestamp":1611986134,"openPRs":214,"mergedPRs":13930,"openIssues":368,"closedIssues":11624,"closedPRs":2692},{"openPRs":214,"stars":48823,"timestamp":1611983058,"closedPRs":2692,"openIssues":368,"mergedPRs":13930,"closedIssues":11624},{"stars":48821,"timestamp":1611979331,"openPRs":214,"closedIssues":11624,"openIssues":368,"closedPRs":2692,"mergedPRs":13930},{"stars":48821,"openPRs":214,"closedIssues":11624,"openIssues":368,"timestamp":1611975858,"closedPRs":2692,"mergedPRs":13930},{"timestamp":1611973194,"openPRs":214,"closedIssues":11624,"stars":48821,"openIssues":368,"closedPRs":2692,"mergedPRs":13930},{"closedIssues":11624,"stars":48821,"openPRs":214,"closedPRs":2692,"mergedPRs":13930,"timestamp":1611970828,"openIssues":368},{"closedIssues":11624,"openPRs":214,"mergedPRs":13930,"closedPRs":2692,"stars":48822,"openIssues":368,"timestamp":1611964794},{"timestamp":1611961253,"mergedPRs":13930,"openIssues":368,"openPRs":214,"stars":48820,"closedPRs":2692,"closedIssues":11624},{"closedIssues":11624,"openPRs":214,"openIssues":368,"closedPRs":2692,"timestamp":1611957423,"mergedPRs":13930,"stars":48820},{"mergedPRs":13930,"openPRs":214,"closedIssues":11624,"closedPRs":2692,"stars":48820,"timestamp":1611953761,"openIssues":367},{"closedIssues":11624,"mergedPRs":13930,"openPRs":214,"timestamp":1611950245,"stars":48821,"openIssues":367,"closedPRs":2692},{"openPRs":214,"openIssues":367,"timestamp":1611947515,"closedIssues":11624,"stars":48820,"closedPRs":2692,"mergedPRs":13930},{"closedIssues":11624,"timestamp":1611944091,"openIssues":367,"stars":48822,"openPRs":215,"closedPRs":2692,"mergedPRs":13929},{"openPRs":215,"mergedPRs":13929,"closedIssues":11624,"openIssues":367,"timestamp":1611941406,"stars":48819,"closedPRs":2692},{"timestamp":1611936112,"openIssues":367,"closedPRs":2692,"openPRs":215,"closedIssues":11624,"mergedPRs":13928,"stars":48819},{"mergedPRs":13927,"timestamp":1611932223,"closedPRs":2692,"stars":48819,"openIssues":367,"closedIssues":11624,"openPRs":215},{"timestamp":1611928538,"openIssues":367,"openPRs":214,"closedPRs":2692,"closedIssues":11624,"mergedPRs":13927,"stars":48818},{"closedPRs":2692,"closedIssues":11624,"openPRs":214,"openIssues":367,"mergedPRs":13927,"stars":48817,"timestamp":1611925877},{"openIssues":366,"stars":48816,"openPRs":213,"closedPRs":2692,"closedIssues":11624,"timestamp":1611921273,"mergedPRs":13927},{"openPRs":213,"timestamp":1611918020,"closedPRs":2692,"stars":48815,"closedIssues":11623,"openIssues":367,"mergedPRs":13927},{"timestamp":1611914556,"closedIssues":11623,"mergedPRs":13927,"stars":48815,"openPRs":213,"closedPRs":2692,"openIssues":367},{"timestamp":1611910994,"closedIssues":11623,"openPRs":214,"closedPRs":2692,"mergedPRs":13926,"openIssues":367,"stars":48814},{"timestamp":1611907000,"closedIssues":11623,"stars":48813,"openIssues":367,"openPRs":215,"closedPRs":2691,"mergedPRs":13926},{"openPRs":215,"closedIssues":11623,"closedPRs":2691,"stars":48812,"timestamp":1611903847,"mergedPRs":13926,"openIssues":367},{"closedPRs":2691,"openIssues":367,"timestamp":1611899846,"closedIssues":11623,"stars":48812,"openPRs":215,"mergedPRs":13926},{"stars":48812,"openIssues":368,"openPRs":215,"timestamp":1611896739,"closedIssues":11622,"closedPRs":2691,"mergedPRs":13926},{"mergedPRs":13926,"timestamp":1611893013,"closedIssues":11622,"closedPRs":2691,"stars":48812,"openPRs":215,"openIssues":368},{"timestamp":1611889473,"closedIssues":11622,"mergedPRs":13926,"stars":48811,"openIssues":368,"openPRs":214,"closedPRs":2691},{"timestamp":1611886753,"mergedPRs":13926,"closedIssues":11622,"closedPRs":2691,"stars":48811,"openPRs":214,"openIssues":367},{"closedPRs":2691,"timestamp":1611884417,"openPRs":214,"closedIssues":11622,"mergedPRs":13926,"openIssues":367,"stars":48810},{"timestamp":1611878531,"openPRs":214,"mergedPRs":13926,"closedIssues":11622,"closedPRs":2691,"stars":48807,"openIssues":367},{"mergedPRs":13926,"timestamp":1611874933,"closedPRs":2691,"openPRs":214,"openIssues":367,"closedIssues":11622,"stars":48807},{"mergedPRs":13926,"closedIssues":11622,"openIssues":367,"closedPRs":2691,"timestamp":1611871072,"openPRs":213,"stars":48807},{"openPRs":212,"closedIssues":11622,"timestamp":1611867403,"closedPRs":2691,"openIssues":364,"mergedPRs":13926,"stars":48806},{"openPRs":212,"stars":48805,"openIssues":363,"closedPRs":2691,"mergedPRs":13926,"timestamp":1611863808,"closedIssues":11622},{"closedIssues":11622,"openPRs":212,"stars":48805,"closedPRs":2691,"mergedPRs":13926,"openIssues":363,"timestamp":1611861087},{"mergedPRs":13926,"openIssues":363,"closedIssues":11622,"timestamp":1611857661,"openPRs":211,"closedPRs":2691,"stars":48805},{"closedIssues":11622,"stars":48804,"closedPRs":2691,"timestamp":1611855016,"openPRs":210,"mergedPRs":13926,"openIssues":363},{"timestamp":1611849709,"mergedPRs":13926,"closedPRs":2684,"stars":48800,"closedIssues":11621,"openIssues":364,"openPRs":216},{"stars":48799,"openIssues":365,"timestamp":1611845802,"closedPRs":2684,"openPRs":230,"mergedPRs":13911,"closedIssues":11620},{"timestamp":1611842157,"openPRs":231,"closedIssues":11620,"closedPRs":2684,"mergedPRs":13910,"openIssues":365,"stars":48799},{"openPRs":231,"closedIssues":11620,"closedPRs":2684,"mergedPRs":13909,"openIssues":365,"stars":48799,"timestamp":1611839491},{"mergedPRs":13907,"openPRs":232,"timestamp":1611834866,"closedPRs":2684,"stars":48800,"closedIssues":11615,"openIssues":370},{"closedIssues":11613,"timestamp":1611831672,"closedPRs":2684,"openIssues":372,"stars":48800,"openPRs":232,"mergedPRs":13906},{"stars":48800,"openIssues":373,"closedPRs":2684,"mergedPRs":13906,"timestamp":1611828174,"openPRs":231,"closedIssues":11612},{"openPRs":231,"closedIssues":11612,"stars":48801,"mergedPRs":13905,"timestamp":1611825816,"openIssues":373,"closedPRs":2684},{"closedIssues":11611,"closedPRs":2684,"openIssues":374,"stars":48800,"mergedPRs":13905,"timestamp":1611823817,"openPRs":230},{"openPRs":230,"closedIssues":11611,"closedPRs":2684,"mergedPRs":13905,"stars":48800,"timestamp":1611822107,"openIssues":374},{"closedPRs":2684,"stars":48799,"closedIssues":11611,"openPRs":230,"timestamp":1611820200,"openIssues":374,"mergedPRs":13905},{"mergedPRs":13905,"closedPRs":2684,"openIssues":374,"openPRs":230,"closedIssues":11611,"timestamp":1611818639,"stars":48799},{"closedIssues":11611,"openIssues":374,"stars":48797,"openPRs":230,"closedPRs":2684,"timestamp":1611803056,"mergedPRs":13905},{"closedPRs":2684,"openIssues":374,"closedIssues":11611,"openPRs":230,"timestamp":1611800391,"stars":48794,"mergedPRs":13905},{"timestamp":1611798135,"openIssues":374,"closedPRs":2684,"mergedPRs":13905,"closedIssues":11611,"openPRs":230,"stars":48794},{"closedIssues":11611,"openIssues":373,"openPRs":230,"closedPRs":2684,"stars":48793,"timestamp":1611792094,"mergedPRs":13905},{"stars":48793,"openIssues":373,"timestamp":1611788491,"closedPRs":2684,"mergedPRs":13905,"openPRs":230,"closedIssues":11611},{"openPRs":229,"stars":48792,"mergedPRs":13905,"timestamp":1611784647,"openIssues":372,"closedIssues":11611,"closedPRs":2684},{"openPRs":228,"stars":48793,"timestamp":1611780969,"mergedPRs":13905,"openIssues":372,"closedIssues":11611,"closedPRs":2684},{"openPRs":230,"timestamp":1611777394,"closedIssues":11611,"openIssues":372,"stars":48792,"mergedPRs":13903,"closedPRs":2684},{"closedPRs":2684,"openIssues":372,"closedIssues":11611,"openPRs":231,"stars":48792,"mergedPRs":13902,"timestamp":1611774606},{"openPRs":230,"timestamp":1611771164,"stars":48791,"openIssues":372,"closedPRs":2684,"mergedPRs":13902,"closedIssues":11611},{"timestamp":1611768478,"closedPRs":2684,"mergedPRs":13902,"closedIssues":11611,"stars":48789,"openIssues":371,"openPRs":229},{"openPRs":229,"stars":48789,"mergedPRs":13901,"timestamp":1611763283,"closedIssues":11611,"closedPRs":2684,"openIssues":371},{"openPRs":227,"timestamp":1611759391,"mergedPRs":13901,"openIssues":371,"stars":48789,"closedPRs":2684,"closedIssues":11611},{"mergedPRs":13900,"closedPRs":2684,"openIssues":371,"openPRs":228,"timestamp":1611755865,"stars":48790,"closedIssues":11611},{"closedIssues":11611,"timestamp":1611753060,"openIssues":371,"openPRs":228,"mergedPRs":13900,"closedPRs":2684,"stars":48790},{"openPRs":227,"closedIssues":11610,"openIssues":371,"stars":48788,"mergedPRs":13899,"timestamp":1611748378,"closedPRs":2684},{"timestamp":1611745171,"mergedPRs":13898,"openPRs":228,"closedIssues":11610,"closedPRs":2684,"stars":48788,"openIssues":371},{"timestamp":1611741687,"closedIssues":11610,"openPRs":227,"openIssues":371,"closedPRs":2684,"mergedPRs":13897,"stars":48788},{"timestamp":1611738153,"stars":48787,"closedIssues":11607,"mergedPRs":13895,"openPRs":229,"openIssues":374,"closedPRs":2684},{"mergedPRs":13895,"openPRs":229,"closedIssues":11607,"timestamp":1611734095,"stars":48784,"openIssues":374,"closedPRs":2684},{"openPRs":237,"closedIssues":11607,"stars":48784,"closedPRs":2681,"timestamp":1611730966,"openIssues":374,"mergedPRs":13890},{"stars":48783,"openPRs":237,"mergedPRs":13890,"timestamp":1611726929,"closedPRs":2681,"openIssues":374,"closedIssues":11607},{"closedPRs":2681,"timestamp":1611723856,"openIssues":374,"mergedPRs":13890,"stars":48783,"closedIssues":11607,"openPRs":237},{"mergedPRs":13890,"stars":48782,"openPRs":237,"openIssues":374,"closedPRs":2681,"closedIssues":11607,"timestamp":1611720136},{"timestamp":1611716596,"stars":48780,"closedPRs":2681,"openPRs":237,"mergedPRs":13890,"closedIssues":11607,"openIssues":374},{"closedPRs":2681,"mergedPRs":13890,"closedIssues":11607,"openPRs":237,"timestamp":1611713961,"openIssues":374,"stars":48781},{"openIssues":374,"timestamp":1611711606,"closedPRs":2681,"closedIssues":11607,"openPRs":237,"mergedPRs":13890,"stars":48781},{"timestamp":1611705567,"openIssues":374,"stars":48781,"closedIssues":11607,"mergedPRs":13890,"closedPRs":2681,"openPRs":237},{"mergedPRs":13890,"stars":48782,"openIssues":374,"closedIssues":11607,"openPRs":237,"timestamp":1611701969,"closedPRs":2681},{"mergedPRs":13890,"stars":48782,"openPRs":236,"timestamp":1611698227,"openIssues":373,"closedIssues":11607,"closedPRs":2681},{"closedPRs":2681,"mergedPRs":13890,"timestamp":1611694552,"openPRs":236,"stars":48781,"closedIssues":11607,"openIssues":372},{"openPRs":236,"closedIssues":11607,"stars":48781,"mergedPRs":13890,"timestamp":1611690950,"openIssues":372,"closedPRs":2681},{"timestamp":1611688140,"openPRs":236,"closedPRs":2681,"stars":48781,"mergedPRs":13890,"openIssues":373,"closedIssues":11606},{"mergedPRs":13890,"closedIssues":11606,"stars":48780,"closedPRs":2681,"openIssues":373,"timestamp":1611684701,"openPRs":236},{"timestamp":1611682009,"mergedPRs":13890,"closedIssues":11606,"openIssues":373,"openPRs":236,"stars":48780,"closedPRs":2681},{"openIssues":372,"openPRs":237,"stars":48780,"closedIssues":11606,"closedPRs":2681,"mergedPRs":13888,"timestamp":1611676876},{"closedPRs":2681,"stars":48780,"openPRs":235,"mergedPRs":13888,"timestamp":1611672942,"closedIssues":11606,"openIssues":372},{"openPRs":232,"stars":48778,"closedPRs":2681,"mergedPRs":13888,"timestamp":1611669312,"closedIssues":11606,"openIssues":372},{"closedPRs":2681,"stars":48779,"timestamp":1611666622,"closedIssues":11606,"mergedPRs":13888,"openIssues":372,"openPRs":232},{"timestamp":1611661960,"closedIssues":11606,"mergedPRs":13888,"closedPRs":2681,"openPRs":232,"openIssues":372,"stars":48779},{"closedIssues":11605,"openIssues":373,"stars":48779,"timestamp":1611658780,"mergedPRs":13888,"openPRs":232,"closedPRs":2681},{"closedPRs":2681,"mergedPRs":13888,"openPRs":232,"stars":48779,"timestamp":1611655283,"closedIssues":11605,"openIssues":373},{"closedIssues":11605,"openIssues":373,"closedPRs":2681,"openPRs":233,"stars":48779,"mergedPRs":13887,"timestamp":1611651761},{"closedPRs":2681,"openIssues":373,"stars":48778,"openPRs":236,"timestamp":1611647715,"closedIssues":11605,"mergedPRs":13884},{"openIssues":373,"timestamp":1611644597,"closedPRs":2681,"mergedPRs":13884,"openPRs":236,"stars":48777,"closedIssues":11605},{"mergedPRs":13884,"timestamp":1611640600,"closedIssues":11605,"openIssues":373,"openPRs":236,"closedPRs":2681,"stars":48776},{"stars":48776,"openPRs":236,"openIssues":373,"timestamp":1611637442,"closedIssues":11605,"mergedPRs":13884,"closedPRs":2681},{"closedPRs":2681,"stars":48776,"openPRs":236,"timestamp":1611633738,"closedIssues":11605,"mergedPRs":13884,"openIssues":373},{"openPRs":236,"timestamp":1611630165,"closedPRs":2681,"mergedPRs":13884,"openIssues":373,"stars":48776,"closedIssues":11605},{"closedIssues":11605,"stars":48777,"openPRs":236,"openIssues":373,"timestamp":1611627533,"closedPRs":2681,"mergedPRs":13884},{"mergedPRs":13884,"timestamp":1611625299,"closedPRs":2681,"openIssues":373,"closedIssues":11605,"stars":48777,"openPRs":236},{"openIssues":374,"mergedPRs":13884,"openPRs":236,"closedPRs":2681,"timestamp":1611619315,"stars":48777,"closedIssues":11604},{"closedIssues":11604,"mergedPRs":13884,"openIssues":374,"timestamp":1611615884,"stars":48777,"closedPRs":2681,"openPRs":235},{"stars":48777,"openPRs":235,"mergedPRs":13884,"timestamp":1611612619,"closedIssues":11604,"openIssues":374,"closedPRs":2681},{"closedPRs":2681,"timestamp":1611609525,"mergedPRs":13884,"openIssues":373,"stars":48776,"openPRs":235,"closedIssues":11604},{"mergedPRs":13884,"stars":48776,"openPRs":235,"closedIssues":11604,"timestamp":1611606234,"closedPRs":2681,"openIssues":372},{"openPRs":234,"closedPRs":2681,"stars":48776,"closedIssues":11604,"openIssues":372,"mergedPRs":13884,"timestamp":1611603529},{"mergedPRs":13883,"openIssues":371,"openPRs":233,"closedPRs":2681,"stars":48777,"timestamp":1611598087,"closedIssues":11604},{"stars":48774,"closedIssues":11604,"openIssues":371,"closedPRs":2681,"mergedPRs":13883,"timestamp":1611591642,"openPRs":232},{"closedPRs":2681,"stars":48774,"mergedPRs":13882,"openPRs":233,"closedIssues":11604,"openIssues":371,"timestamp":1611587798},{"closedPRs":2681,"closedIssues":11604,"openIssues":371,"timestamp":1611584712,"openPRs":230,"stars":48773,"mergedPRs":13882},{"closedIssues":11603,"stars":48773,"mergedPRs":13880,"openIssues":372,"openPRs":232,"closedPRs":2681,"timestamp":1611581870},{"closedPRs":2681,"closedIssues":11601,"openIssues":373,"timestamp":1611577038,"openPRs":233,"stars":48773,"mergedPRs":13879},{"timestamp":1611574323,"openIssues":373,"openPRs":232,"closedPRs":2681,"closedIssues":11601,"mergedPRs":13879,"stars":48771},{"openPRs":231,"closedIssues":11601,"mergedPRs":13879,"openIssues":373,"closedPRs":2681,"stars":48770,"timestamp":1611570801},{"closedPRs":2679,"stars":48770,"closedIssues":11598,"openIssues":376,"timestamp":1611567137,"openPRs":237,"mergedPRs":13874},{"closedIssues":11597,"timestamp":1611563046,"openPRs":237,"closedPRs":2679,"mergedPRs":13874,"openIssues":380,"stars":48769},{"closedIssues":11597,"openIssues":380,"timestamp":1611559935,"openPRs":237,"closedPRs":2679,"stars":48769,"mergedPRs":13874},{"closedIssues":11597,"openPRs":237,"openIssues":380,"mergedPRs":13874,"timestamp":1611555898,"stars":48769,"closedPRs":2679},{"stars":48769,"openPRs":235,"closedPRs":2679,"mergedPRs":13874,"closedIssues":11597,"timestamp":1611552908,"openIssues":380},{"closedPRs":2679,"openPRs":230,"closedIssues":11597,"mergedPRs":13874,"stars":48768,"openIssues":380,"timestamp":1611546613},{"closedPRs":2679,"openPRs":227,"stars":48769,"openIssues":380,"timestamp":1611542006,"closedIssues":11597,"mergedPRs":13874},{"mergedPRs":13874,"closedIssues":11597,"stars":48769,"timestamp":1611534358,"openIssues":380,"closedPRs":2679,"openPRs":223},{"stars":48769,"closedIssues":11597,"timestamp":1611530605,"openPRs":222,"openIssues":380,"mergedPRs":13874,"closedPRs":2679},{"closedPRs":2679,"openPRs":222,"timestamp":1611526741,"openIssues":380,"stars":48767,"closedIssues":11597,"mergedPRs":13874},{"closedIssues":11597,"openPRs":222,"closedPRs":2679,"openIssues":380,"timestamp":1611522989,"stars":48766,"mergedPRs":13874},{"mergedPRs":13874,"stars":48765,"openIssues":380,"closedPRs":2679,"openPRs":222,"timestamp":1611519757,"closedIssues":11597},{"stars":48764,"openPRs":222,"timestamp":1611517054,"closedPRs":2679,"openIssues":380,"mergedPRs":13874,"closedIssues":11597},{"stars":48764,"openIssues":380,"openPRs":222,"closedIssues":11597,"closedPRs":2679,"mergedPRs":13874,"timestamp":1611511626},{"timestamp":1611505154,"mergedPRs":13874,"openIssues":379,"closedPRs":2679,"stars":48764,"openPRs":222,"closedIssues":11597},{"closedIssues":11597,"openIssues":378,"timestamp":1611501236,"mergedPRs":13874,"stars":48764,"openPRs":222,"closedPRs":2679},{"closedPRs":2679,"openIssues":378,"stars":48764,"mergedPRs":13874,"timestamp":1611498146,"openPRs":222,"closedIssues":11597},{"stars":48763,"openIssues":378,"openPRs":222,"timestamp":1611495326,"closedPRs":2679,"closedIssues":11597,"mergedPRs":13874},{"stars":48761,"openPRs":222,"timestamp":1611490541,"closedIssues":11597,"openIssues":378,"closedPRs":2679,"mergedPRs":13874},{"mergedPRs":13874,"closedPRs":2679,"timestamp":1611487732,"openIssues":378,"stars":48760,"closedIssues":11597,"openPRs":222},{"closedPRs":2679,"stars":48760,"timestamp":1611484210,"openIssues":378,"openPRs":221,"closedIssues":11597,"mergedPRs":13874},{"mergedPRs":13874,"timestamp":1611480587,"closedPRs":2679,"openPRs":220,"openIssues":378,"closedIssues":11597,"stars":48760},{"closedIssues":11597,"mergedPRs":13874,"openPRs":220,"stars":48759,"openIssues":378,"closedPRs":2679,"timestamp":1611476560},{"openPRs":220,"closedIssues":11597,"stars":48758,"openIssues":378,"mergedPRs":13874,"closedPRs":2679,"timestamp":1611473457},{"closedIssues":11597,"openIssues":378,"stars":48756,"timestamp":1611469471,"mergedPRs":13874,"openPRs":220,"closedPRs":2679},{"timestamp":1611466549,"stars":48756,"openPRs":220,"closedPRs":2679,"closedIssues":11597,"openIssues":378,"mergedPRs":13874},{"stars":48755,"openIssues":378,"timestamp":1611460218,"openPRs":220,"closedIssues":11597,"mergedPRs":13874,"closedPRs":2679},{"mergedPRs":13874,"closedIssues":11597,"openIssues":378,"closedPRs":2679,"openPRs":220,"stars":48753,"timestamp":1611455661},{"openPRs":220,"closedPRs":2679,"closedIssues":11597,"stars":48753,"openIssues":378,"mergedPRs":13874,"timestamp":1611447913},{"timestamp":1611444149,"openIssues":377,"openPRs":220,"closedIssues":11597,"closedPRs":2679,"stars":48752,"mergedPRs":13874},{"timestamp":1611439992,"openPRs":220,"closedIssues":11597,"openIssues":377,"closedPRs":2679,"mergedPRs":13874,"stars":48751},{"mergedPRs":13874,"stars":48749,"openIssues":377,"closedPRs":2679,"timestamp":1611436504,"closedIssues":11597,"openPRs":220},{"timestamp":1611433260,"mergedPRs":13874,"closedPRs":2679,"closedIssues":11597,"openIssues":377,"stars":48749,"openPRs":220},{"closedIssues":11597,"closedPRs":2679,"timestamp":1611430579,"stars":48748,"openPRs":220,"openIssues":377,"mergedPRs":13874},{"closedIssues":11597,"closedPRs":2679,"timestamp":1611425146,"openIssues":376,"stars":48748,"openPRs":220,"mergedPRs":13874},{"timestamp":1611418682,"closedIssues":11597,"closedPRs":2679,"mergedPRs":13874,"openIssues":376,"openPRs":220,"stars":48746},{"openPRs":220,"stars":48746,"openIssues":376,"mergedPRs":13874,"timestamp":1611414793,"closedPRs":2679,"closedIssues":11597},{"closedIssues":11597,"openPRs":220,"openIssues":376,"mergedPRs":13874,"closedPRs":2679,"stars":48745,"timestamp":1611411712},{"openPRs":220,"mergedPRs":13874,"stars":48746,"timestamp":1611408860,"closedPRs":2679,"openIssues":376,"closedIssues":11597},{"timestamp":1611404077,"closedIssues":11597,"stars":48746,"openPRs":219,"openIssues":376,"closedPRs":2679,"mergedPRs":13874},{"closedIssues":11597,"stars":48747,"mergedPRs":13874,"openPRs":219,"openIssues":375,"closedPRs":2679,"timestamp":1611401292},{"timestamp":1611397762,"closedIssues":11596,"openPRs":219,"mergedPRs":13874,"openIssues":375,"stars":48746,"closedPRs":2679},{"mergedPRs":13874,"openIssues":375,"timestamp":1611394127,"closedPRs":2679,"stars":48745,"closedIssues":11596,"openPRs":219},{"openIssues":375,"timestamp":1611390108,"openPRs":219,"closedPRs":2679,"closedIssues":11596,"mergedPRs":13874,"stars":48744},{"closedIssues":11596,"closedPRs":2679,"openPRs":219,"mergedPRs":13874,"openIssues":374,"timestamp":1611386949,"stars":48744},{"timestamp":1611382987,"stars":48744,"openIssues":374,"openPRs":219,"mergedPRs":13874,"closedIssues":11596,"closedPRs":2679}]
