[{"mergedPRs":13883,"openPRs":233,"closedIssues":11604,"stars":48777,"openIssues":371,"closedPRs":2681,"timestamp":1611598087},{"stars":48774,"closedPRs":2681,"openPRs":232,"mergedPRs":13883,"closedIssues":11604,"timestamp":1611591642,"openIssues":371},{"closedIssues":11604,"openPRs":233,"stars":48774,"mergedPRs":13882,"openIssues":371,"timestamp":1611587798,"closedPRs":2681},{"closedIssues":11604,"mergedPRs":13882,"timestamp":1611584712,"openPRs":230,"closedPRs":2681,"openIssues":371,"stars":48773},{"closedIssues":11603,"timestamp":1611581870,"closedPRs":2681,"openPRs":232,"mergedPRs":13880,"stars":48773,"openIssues":372},{"closedPRs":2681,"timestamp":1611577038,"openPRs":233,"openIssues":373,"mergedPRs":13879,"stars":48773,"closedIssues":11601},{"stars":48771,"closedPRs":2681,"timestamp":1611574323,"openPRs":232,"closedIssues":11601,"openIssues":373,"mergedPRs":13879},{"openPRs":231,"stars":48770,"openIssues":373,"closedPRs":2681,"timestamp":1611570801,"closedIssues":11601,"mergedPRs":13879},{"openPRs":237,"stars":48770,"mergedPRs":13874,"closedPRs":2679,"timestamp":1611567137,"closedIssues":11598,"openIssues":376},{"closedIssues":11597,"closedPRs":2679,"openIssues":380,"timestamp":1611563046,"openPRs":237,"mergedPRs":13874,"stars":48769},{"timestamp":1611559935,"openPRs":237,"stars":48769,"openIssues":380,"closedIssues":11597,"mergedPRs":13874,"closedPRs":2679},{"closedPRs":2679,"stars":48769,"timestamp":1611555898,"openIssues":380,"openPRs":237,"mergedPRs":13874,"closedIssues":11597},{"openPRs":235,"timestamp":1611552908,"stars":48769,"mergedPRs":13874,"closedIssues":11597,"openIssues":380,"closedPRs":2679},{"openPRs":230,"openIssues":380,"closedPRs":2679,"stars":48768,"mergedPRs":13874,"timestamp":1611546613,"closedIssues":11597},{"openIssues":380,"closedPRs":2679,"openPRs":227,"mergedPRs":13874,"closedIssues":11597,"timestamp":1611542006,"stars":48769},{"stars":48769,"closedPRs":2679,"timestamp":1611534358,"openPRs":223,"mergedPRs":13874,"openIssues":380,"closedIssues":11597},{"openIssues":380,"openPRs":222,"closedPRs":2679,"stars":48769,"mergedPRs":13874,"timestamp":1611530605,"closedIssues":11597},{"closedIssues":11597,"timestamp":1611526741,"openIssues":380,"openPRs":222,"stars":48767,"mergedPRs":13874,"closedPRs":2679},{"timestamp":1611522989,"closedIssues":11597,"openPRs":222,"mergedPRs":13874,"closedPRs":2679,"openIssues":380,"stars":48766},{"closedPRs":2679,"stars":48765,"mergedPRs":13874,"openIssues":380,"openPRs":222,"closedIssues":11597,"timestamp":1611519757},{"openIssues":380,"openPRs":222,"timestamp":1611517054,"mergedPRs":13874,"closedPRs":2679,"closedIssues":11597,"stars":48764},{"closedIssues":11597,"mergedPRs":13874,"openPRs":222,"stars":48764,"openIssues":380,"timestamp":1611511626,"closedPRs":2679},{"timestamp":1611505154,"mergedPRs":13874,"openPRs":222,"stars":48764,"closedPRs":2679,"openIssues":379,"closedIssues":11597},{"closedPRs":2679,"timestamp":1611501236,"openIssues":378,"mergedPRs":13874,"openPRs":222,"closedIssues":11597,"stars":48764},{"timestamp":1611498146,"closedIssues":11597,"closedPRs":2679,"openPRs":222,"mergedPRs":13874,"stars":48764,"openIssues":378},{"openPRs":222,"mergedPRs":13874,"openIssues":378,"stars":48763,"timestamp":1611495326,"closedIssues":11597,"closedPRs":2679},{"timestamp":1611490541,"openIssues":378,"openPRs":222,"stars":48761,"mergedPRs":13874,"closedIssues":11597,"closedPRs":2679},{"openIssues":378,"closedPRs":2679,"stars":48760,"closedIssues":11597,"mergedPRs":13874,"timestamp":1611487732,"openPRs":222},{"mergedPRs":13874,"openIssues":378,"timestamp":1611484210,"closedPRs":2679,"openPRs":221,"closedIssues":11597,"stars":48760},{"stars":48760,"timestamp":1611480587,"openPRs":220,"closedIssues":11597,"closedPRs":2679,"mergedPRs":13874,"openIssues":378},{"closedIssues":11597,"mergedPRs":13874,"closedPRs":2679,"openPRs":220,"timestamp":1611476560,"stars":48759,"openIssues":378},{"closedIssues":11597,"timestamp":1611473457,"closedPRs":2679,"stars":48758,"openPRs":220,"mergedPRs":13874,"openIssues":378},{"openPRs":220,"closedIssues":11597,"stars":48756,"openIssues":378,"closedPRs":2679,"timestamp":1611469471,"mergedPRs":13874},{"openIssues":378,"timestamp":1611466549,"closedPRs":2679,"stars":48756,"openPRs":220,"mergedPRs":13874,"closedIssues":11597},{"closedIssues":11597,"mergedPRs":13874,"openPRs":220,"closedPRs":2679,"openIssues":378,"timestamp":1611460218,"stars":48755},{"closedIssues":11597,"timestamp":1611455661,"closedPRs":2679,"mergedPRs":13874,"stars":48753,"openIssues":378,"openPRs":220},{"openIssues":378,"mergedPRs":13874,"openPRs":220,"closedIssues":11597,"stars":48753,"timestamp":1611447913,"closedPRs":2679},{"timestamp":1611444149,"openIssues":377,"stars":48752,"closedIssues":11597,"closedPRs":2679,"openPRs":220,"mergedPRs":13874},{"openPRs":220,"closedPRs":2679,"timestamp":1611439992,"stars":48751,"openIssues":377,"closedIssues":11597,"mergedPRs":13874},{"stars":48749,"closedIssues":11597,"openIssues":377,"mergedPRs":13874,"timestamp":1611436504,"openPRs":220,"closedPRs":2679},{"timestamp":1611433260,"openIssues":377,"closedPRs":2679,"stars":48749,"closedIssues":11597,"openPRs":220,"mergedPRs":13874},{"openIssues":377,"timestamp":1611430579,"closedPRs":2679,"openPRs":220,"closedIssues":11597,"mergedPRs":13874,"stars":48748},{"timestamp":1611425146,"stars":48748,"closedIssues":11597,"mergedPRs":13874,"openPRs":220,"openIssues":376,"closedPRs":2679},{"openPRs":220,"timestamp":1611418682,"stars":48746,"openIssues":376,"closedPRs":2679,"closedIssues":11597,"mergedPRs":13874},{"closedIssues":11597,"openIssues":376,"openPRs":220,"mergedPRs":13874,"timestamp":1611414793,"closedPRs":2679,"stars":48746},{"openPRs":220,"closedIssues":11597,"mergedPRs":13874,"openIssues":376,"timestamp":1611411712,"stars":48745,"closedPRs":2679},{"mergedPRs":13874,"openPRs":220,"closedPRs":2679,"timestamp":1611408860,"closedIssues":11597,"stars":48746,"openIssues":376},{"timestamp":1611404077,"closedIssues":11597,"stars":48746,"openIssues":376,"closedPRs":2679,"openPRs":219,"mergedPRs":13874},{"openIssues":375,"openPRs":219,"mergedPRs":13874,"stars":48747,"closedIssues":11597,"closedPRs":2679,"timestamp":1611401292},{"stars":48746,"closedPRs":2679,"closedIssues":11596,"mergedPRs":13874,"timestamp":1611397762,"openPRs":219,"openIssues":375},{"openIssues":375,"closedIssues":11596,"closedPRs":2679,"stars":48745,"mergedPRs":13874,"timestamp":1611394127,"openPRs":219},{"closedPRs":2679,"closedIssues":11596,"openIssues":375,"timestamp":1611390108,"openPRs":219,"stars":48744,"mergedPRs":13874},{"openPRs":219,"closedIssues":11596,"openIssues":374,"closedPRs":2679,"timestamp":1611386949,"stars":48744,"mergedPRs":13874},{"closedIssues":11596,"openIssues":374,"mergedPRs":13874,"openPRs":219,"timestamp":1611382987,"closedPRs":2679,"stars":48744},{"closedIssues":11596,"stars":48744,"openPRs":219,"mergedPRs":13874,"openIssues":373,"closedPRs":2679,"timestamp":1611380001},{"openPRs":219,"closedIssues":11596,"mergedPRs":13874,"openIssues":373,"timestamp":1611373650,"stars":48743,"closedPRs":2679},{"openIssues":373,"closedPRs":2679,"mergedPRs":13874,"openPRs":219,"closedIssues":11596,"timestamp":1611369148,"stars":48742},{"stars":48742,"openPRs":219,"closedPRs":2679,"mergedPRs":13874,"timestamp":1611361696,"openIssues":372,"closedIssues":11596},{"closedPRs":2679,"closedIssues":11596,"stars":48741,"openPRs":218,"mergedPRs":13874,"timestamp":1611357920,"openIssues":372},{"timestamp":1611353739,"mergedPRs":13874,"openIssues":372,"stars":48740,"closedIssues":11596,"openPRs":218,"closedPRs":2679},{"openIssues":372,"mergedPRs":13874,"openPRs":218,"closedIssues":11596,"timestamp":1611350336,"stars":48740,"closedPRs":2679},{"closedPRs":2679,"mergedPRs":13874,"openIssues":372,"openPRs":218,"stars":48740,"timestamp":1611347060,"closedIssues":11596},{"mergedPRs":13874,"openIssues":372,"openPRs":218,"closedPRs":2679,"closedIssues":11596,"timestamp":1611344368,"stars":48740},{"closedIssues":11596,"openIssues":372,"stars":48740,"timestamp":1611338924,"closedPRs":2679,"openPRs":218,"mergedPRs":13874},{"closedIssues":11596,"closedPRs":2679,"mergedPRs":13874,"timestamp":1611332435,"openPRs":216,"openIssues":372,"stars":48741},{"timestamp":1611328526,"stars":48741,"closedPRs":2679,"closedIssues":11596,"openPRs":218,"mergedPRs":13872,"openIssues":372},{"closedPRs":2679,"timestamp":1611325504,"stars":48740,"closedIssues":11596,"openPRs":219,"mergedPRs":13871,"openIssues":372},{"closedPRs":2679,"stars":48737,"openIssues":372,"timestamp":1611322653,"mergedPRs":13870,"closedIssues":11596,"openPRs":220},{"mergedPRs":13870,"openPRs":218,"openIssues":371,"timestamp":1611317840,"closedPRs":2679,"closedIssues":11596,"stars":48736},{"timestamp":1611315102,"mergedPRs":13870,"openPRs":217,"stars":48736,"closedIssues":11596,"closedPRs":2679,"openIssues":371},{"closedIssues":11596,"mergedPRs":13870,"openPRs":215,"closedPRs":2679,"stars":48736,"timestamp":1611311576,"openIssues":371},{"openIssues":377,"timestamp":1611307899,"openPRs":215,"stars":48736,"closedIssues":11589,"closedPRs":2679,"mergedPRs":13869},{"stars":48735,"closedIssues":11589,"openIssues":377,"timestamp":1611303836,"closedPRs":2679,"mergedPRs":13869,"openPRs":215},{"timestamp":1611300728,"openPRs":215,"openIssues":377,"mergedPRs":13869,"stars":48735,"closedIssues":11589,"closedPRs":2679},{"closedIssues":11589,"stars":48734,"timestamp":1611296720,"closedPRs":2679,"openPRs":215,"openIssues":377,"mergedPRs":13869},{"openPRs":215,"closedIssues":11589,"mergedPRs":13869,"openIssues":377,"closedPRs":2679,"timestamp":1611293720,"stars":48734},{"openIssues":377,"openPRs":215,"stars":48734,"closedPRs":2679,"timestamp":1611287340,"mergedPRs":13869,"closedIssues":11589},{"closedIssues":11589,"stars":48734,"closedPRs":2679,"openIssues":377,"openPRs":214,"mergedPRs":13869,"timestamp":1611282755},{"closedPRs":2679,"openIssues":377,"openPRs":214,"mergedPRs":13869,"closedIssues":11589,"stars":48735,"timestamp":1611275225},{"openPRs":214,"mergedPRs":13869,"timestamp":1611271431,"closedIssues":11589,"closedPRs":2679,"openIssues":377,"stars":48734},{"timestamp":1611267270,"closedPRs":2679,"openIssues":375,"openPRs":214,"closedIssues":11590,"mergedPRs":13869,"stars":48734},{"mergedPRs":13869,"stars":48734,"closedIssues":11590,"openPRs":214,"timestamp":1611263831,"closedPRs":2679,"openIssues":374},{"closedPRs":2679,"openIssues":374,"openPRs":214,"timestamp":1611260523,"closedIssues":11590,"mergedPRs":13869,"stars":48733},{"openPRs":214,"mergedPRs":13869,"stars":48731,"closedIssues":11590,"closedPRs":2679,"timestamp":1611257897,"openIssues":374},{"openPRs":214,"timestamp":1611252486,"stars":48730,"mergedPRs":13868,"closedIssues":11590,"closedPRs":2679,"openIssues":374},{"openPRs":214,"mergedPRs":13868,"timestamp":1611246053,"closedPRs":2679,"closedIssues":11590,"stars":48730,"openIssues":374},{"openIssues":374,"mergedPRs":13868,"closedIssues":11590,"stars":48729,"openPRs":214,"closedPRs":2679,"timestamp":1611242082},{"closedIssues":11590,"stars":48729,"openPRs":213,"openIssues":374,"timestamp":1611239078,"closedPRs":2679,"mergedPRs":13868},{"timestamp":1611236340,"closedPRs":2679,"openIssues":374,"mergedPRs":13867,"openPRs":214,"stars":48728,"closedIssues":11590},{"closedIssues":11590,"stars":48726,"openPRs":212,"mergedPRs":13867,"closedPRs":2679,"timestamp":1611231496,"openIssues":374},{"timestamp":1611228773,"openPRs":213,"closedPRs":2679,"mergedPRs":13866,"stars":48726,"openIssues":375,"closedIssues":11589},{"stars":48724,"closedIssues":11589,"openPRs":212,"timestamp":1611225220,"mergedPRs":13866,"closedPRs":2679,"openIssues":375},{"mergedPRs":13866,"closedIssues":11589,"openIssues":374,"closedPRs":2679,"timestamp":1611221581,"openPRs":212,"stars":48724},{"timestamp":1611217523,"openPRs":213,"closedIssues":11588,"stars":48722,"mergedPRs":13865,"openIssues":375,"closedPRs":2679},{"openPRs":213,"stars":48722,"closedIssues":11588,"timestamp":1611214384,"closedPRs":2679,"mergedPRs":13865,"openIssues":375},{"timestamp":1611210364,"closedIssues":11588,"closedPRs":2679,"openIssues":374,"openPRs":213,"stars":48721,"mergedPRs":13865},{"stars":48721,"closedIssues":11588,"timestamp":1611207333,"openPRs":213,"mergedPRs":13865,"openIssues":374,"closedPRs":2679},{"stars":48720,"mergedPRs":13865,"timestamp":1611200996,"closedIssues":11588,"closedPRs":2679,"openIssues":374,"openPRs":213},{"openPRs":213,"mergedPRs":13865,"stars":48718,"timestamp":1611196434,"closedIssues":11588,"openIssues":372,"closedPRs":2679},{"openIssues":372,"mergedPRs":13865,"openPRs":213,"closedIssues":11588,"stars":48716,"closedPRs":2679,"timestamp":1611188998},{"closedIssues":11588,"closedPRs":2679,"openIssues":372,"timestamp":1611185022,"stars":48716,"openPRs":212,"mergedPRs":13865},{"closedIssues":11588,"openPRs":212,"stars":48714,"openIssues":371,"timestamp":1611180750,"mergedPRs":13865,"closedPRs":2679},{"openIssues":370,"mergedPRs":13865,"closedIssues":11588,"timestamp":1611177598,"openPRs":212,"stars":48715,"closedPRs":2679},{"timestamp":1611174208,"stars":48714,"closedIssues":11588,"closedPRs":2679,"openPRs":212,"openIssues":370,"mergedPRs":13865},{"openPRs":212,"closedIssues":11588,"openIssues":370,"timestamp":1611171604,"mergedPRs":13865,"stars":48712,"closedPRs":2679},{"closedPRs":2679,"timestamp":1611166176,"openPRs":213,"closedIssues":11587,"openIssues":370,"mergedPRs":13864,"stars":48712},{"openIssues":370,"timestamp":1611160233,"closedPRs":2679,"mergedPRs":13862,"closedIssues":11587,"stars":48711,"openPRs":213},{"openIssues":369,"mergedPRs":13861,"openPRs":213,"closedIssues":11587,"timestamp":1611155692,"closedPRs":2679,"stars":48710},{"stars":48708,"closedPRs":2679,"timestamp":1611152719,"mergedPRs":13860,"openIssues":368,"closedIssues":11587,"openPRs":212},{"timestamp":1611149922,"closedIssues":11587,"mergedPRs":13860,"openIssues":368,"closedPRs":2679,"stars":48707,"openPRs":211},{"closedIssues":11587,"openPRs":211,"closedPRs":2679,"stars":48704,"timestamp":1611145089,"mergedPRs":13860,"openIssues":368},{"closedPRs":2679,"closedIssues":11587,"stars":48704,"openIssues":367,"openPRs":212,"mergedPRs":13859,"timestamp":1611142399},{"timestamp":1611138889,"openPRs":212,"closedPRs":2679,"mergedPRs":13859,"stars":48703,"openIssues":368,"closedIssues":11586},{"closedIssues":11586,"mergedPRs":13859,"stars":48703,"openPRs":212,"timestamp":1611135251,"closedPRs":2679,"openIssues":368},{"closedIssues":11586,"closedPRs":2679,"mergedPRs":13859,"timestamp":1611131247,"openPRs":212,"openIssues":368,"stars":48703},{"mergedPRs":13859,"closedIssues":11585,"stars":48704,"openIssues":369,"timestamp":1611128020,"openPRs":212,"closedPRs":2679},{"openPRs":212,"stars":48703,"mergedPRs":13859,"closedIssues":11585,"closedPRs":2679,"timestamp":1611124021,"openIssues":369},{"timestamp":1611121002,"openIssues":369,"mergedPRs":13859,"closedIssues":11585,"stars":48702,"closedPRs":2679,"openPRs":212},{"stars":48704,"closedPRs":2679,"mergedPRs":13859,"closedIssues":11585,"timestamp":1611114610,"openPRs":212,"openIssues":369},{"closedIssues":11585,"timestamp":1611110033,"openPRs":212,"closedPRs":2679,"mergedPRs":13859,"openIssues":369,"stars":48703},{"closedIssues":11585,"openPRs":212,"mergedPRs":13858,"stars":48704,"closedPRs":2679,"timestamp":1611102654,"openIssues":369},{"openPRs":211,"openIssues":369,"closedPRs":2679,"mergedPRs":13858,"closedIssues":11585,"timestamp":1611098800,"stars":48702},{"closedPRs":2679,"timestamp":1611094570,"closedIssues":11585,"stars":48702,"openPRs":210,"mergedPRs":13858,"openIssues":368},{"closedIssues":11585,"closedPRs":2679,"openIssues":368,"mergedPRs":13858,"openPRs":210,"timestamp":1611091184,"stars":48701},{"openPRs":210,"openIssues":368,"closedIssues":11585,"mergedPRs":13858,"closedPRs":2679,"stars":48699,"timestamp":1611087921},{"openIssues":368,"mergedPRs":13856,"openPRs":212,"stars":48697,"timestamp":1611085109,"closedPRs":2679,"closedIssues":11585},{"openPRs":214,"timestamp":1611079624,"closedIssues":11585,"closedPRs":2679,"mergedPRs":13853,"openIssues":368,"stars":48697},{"timestamp":1611073204,"mergedPRs":13852,"stars":48698,"openPRs":213,"openIssues":368,"closedIssues":11585,"closedPRs":2679},{"openPRs":213,"closedIssues":11585,"mergedPRs":13852,"stars":48697,"timestamp":1611069179,"openIssues":368,"closedPRs":2679},{"mergedPRs":13852,"closedIssues":11585,"timestamp":1611066473,"stars":48696,"openPRs":212,"closedPRs":2679,"openIssues":368},{"openPRs":212,"closedPRs":2679,"stars":48695,"openIssues":368,"timestamp":1611063534,"mergedPRs":13852,"closedIssues":11585},{"mergedPRs":13852,"stars":48694,"timestamp":1611055985,"openPRs":212,"openIssues":368,"closedIssues":11585,"closedPRs":2679},{"timestamp":1611052471,"closedIssues":11585,"openIssues":367,"closedPRs":2679,"mergedPRs":13852,"openPRs":211,"stars":48693},{"openPRs":212,"timestamp":1611048758,"closedIssues":11584,"openIssues":368,"closedPRs":2679,"stars":48690,"mergedPRs":13850},{"timestamp":1611044632,"stars":48689,"closedIssues":11584,"closedPRs":2679,"mergedPRs":13850,"openIssues":367,"openPRs":212},{"timestamp":1611041441,"stars":48689,"openPRs":212,"closedIssues":11584,"openIssues":367,"mergedPRs":13850,"closedPRs":2679},{"closedPRs":2679,"timestamp":1611037474,"stars":48686,"openPRs":212,"mergedPRs":13850,"openIssues":366,"closedIssues":11584},{"stars":48686,"openPRs":212,"closedIssues":11584,"closedPRs":2679,"openIssues":366,"timestamp":1611034388,"mergedPRs":13850},{"timestamp":1611028031,"closedPRs":2679,"openIssues":366,"closedIssues":11584,"stars":48686,"openPRs":212,"mergedPRs":13850},{"timestamp":1611023501,"openPRs":212,"openIssues":366,"mergedPRs":13850,"closedPRs":2679,"closedIssues":11584,"stars":48686},{"timestamp":1611016151,"closedIssues":11584,"mergedPRs":13850,"openIssues":365,"closedPRs":2679,"stars":48683,"openPRs":212},{"stars":48683,"mergedPRs":13850,"openPRs":212,"closedIssues":11584,"closedPRs":2679,"timestamp":1611012357,"openIssues":365},{"closedPRs":2679,"openPRs":212,"closedIssues":11584,"mergedPRs":13850,"timestamp":1611008127,"stars":48683,"openIssues":365},{"mergedPRs":13850,"closedPRs":2679,"openPRs":212,"timestamp":1611004719,"openIssues":365,"stars":48683,"closedIssues":11584},{"openPRs":211,"closedIssues":11584,"timestamp":1611001476,"mergedPRs":13850,"openIssues":365,"closedPRs":2679,"stars":48682},{"openPRs":211,"closedIssues":11584,"openIssues":365,"timestamp":1610998706,"stars":48682,"closedPRs":2679,"mergedPRs":13850},{"openIssues":365,"closedPRs":2679,"openPRs":212,"closedIssues":11584,"stars":48681,"mergedPRs":13848,"timestamp":1610993342},{"closedPRs":2679,"openPRs":211,"mergedPRs":13846,"closedIssues":11584,"openIssues":364,"timestamp":1610986775,"stars":48680},{"mergedPRs":13846,"openPRs":209,"closedIssues":11584,"stars":48679,"closedPRs":2679,"openIssues":363,"timestamp":1610982867},{"closedIssues":11582,"stars":48679,"openIssues":364,"timestamp":1610979862,"closedPRs":2678,"mergedPRs":13845,"openPRs":210},{"timestamp":1610976985,"stars":48679,"closedPRs":2678,"closedIssues":11582,"openIssues":364,"openPRs":209,"mergedPRs":13845},{"openIssues":367,"timestamp":1610972221,"stars":48678,"closedIssues":11578,"closedPRs":2678,"openPRs":209,"mergedPRs":13843},{"timestamp":1610969465,"mergedPRs":13843,"openIssues":367,"openPRs":208,"closedIssues":11578,"closedPRs":2678,"stars":48678},{"openPRs":209,"closedIssues":11576,"stars":48677,"mergedPRs":13842,"timestamp":1610965929,"closedPRs":2678,"openIssues":368},{"openPRs":210,"stars":48676,"openIssues":371,"timestamp":1610962229,"closedPRs":2678,"closedIssues":11573,"mergedPRs":13841},{"closedIssues":11573,"stars":48676,"closedPRs":2678,"openIssues":371,"timestamp":1610958177,"mergedPRs":13841,"openPRs":210},{"mergedPRs":13841,"stars":48677,"timestamp":1610954937,"openIssues":371,"openPRs":210,"closedIssues":11573,"closedPRs":2678},{"timestamp":1610950947,"stars":48677,"openPRs":210,"closedIssues":11573,"openIssues":371,"mergedPRs":13841,"closedPRs":2678},{"closedPRs":2678,"stars":48677,"closedIssues":11573,"timestamp":1610947872,"mergedPRs":13841,"openIssues":371,"openPRs":210},{"closedPRs":2678,"mergedPRs":13841,"openIssues":371,"timestamp":1610943771,"closedIssues":11573,"openPRs":210,"stars":48677},{"closedIssues":11573,"openIssues":371,"openPRs":210,"stars":48677,"closedPRs":2678,"timestamp":1610941407,"mergedPRs":13841},{"openPRs":210,"timestamp":1610936914,"stars":48678,"openIssues":371,"closedPRs":2678,"mergedPRs":13841,"closedIssues":11573},{"closedIssues":11573,"mergedPRs":13841,"stars":48678,"openPRs":210,"timestamp":1610929479,"closedPRs":2678,"openIssues":371},{"closedPRs":2678,"timestamp":1610925715,"mergedPRs":13841,"closedIssues":11573,"openPRs":210,"stars":48678,"openIssues":371},{"timestamp":1610921517,"openIssues":371,"openPRs":210,"closedPRs":2678,"closedIssues":11573,"mergedPRs":13841,"stars":48677},{"mergedPRs":13841,"timestamp":1610917996,"stars":48676,"openPRs":210,"openIssues":371,"closedIssues":11573,"closedPRs":2678},{"stars":48676,"timestamp":1610914809,"mergedPRs":13841,"closedPRs":2678,"openIssues":371,"closedIssues":11573,"openPRs":209},{"closedPRs":2678,"openPRs":209,"closedIssues":11573,"mergedPRs":13841,"openIssues":371,"stars":48675,"timestamp":1610912118},{"timestamp":1610906730,"openIssues":370,"mergedPRs":13841,"stars":48675,"closedIssues":11573,"openPRs":209,"closedPRs":2678},{"closedIssues":11573,"stars":48673,"mergedPRs":13841,"openIssues":369,"openPRs":209,"timestamp":1610900206,"closedPRs":2678},{"stars":48672,"closedPRs":2678,"mergedPRs":13841,"openIssues":369,"closedIssues":11573,"timestamp":1610896207,"openPRs":209},{"openPRs":209,"openIssues":369,"stars":48672,"mergedPRs":13841,"closedPRs":2678,"timestamp":1610893171,"closedIssues":11573},{"stars":48671,"closedPRs":2678,"closedIssues":11573,"timestamp":1610890342,"openPRs":209,"openIssues":369,"mergedPRs":13841},{"timestamp":1610885608,"stars":48669,"closedPRs":2678,"openPRs":209,"mergedPRs":13841,"openIssues":369,"closedIssues":11573},{"openIssues":369,"stars":48669,"closedIssues":11573,"timestamp":1610882782,"mergedPRs":13841,"closedPRs":2678,"openPRs":209},{"closedPRs":2678,"openIssues":368,"mergedPRs":13841,"closedIssues":11573,"stars":48669,"timestamp":1610879282,"openPRs":209},{"openIssues":368,"closedPRs":2678,"mergedPRs":13841,"stars":48669,"openPRs":209,"closedIssues":11573,"timestamp":1610875630},{"openPRs":209,"closedPRs":2678,"mergedPRs":13841,"stars":48668,"openIssues":367,"closedIssues":11573,"timestamp":1610871625},{"timestamp":1610868435,"closedIssues":11573,"openPRs":209,"closedPRs":2678,"openIssues":367,"mergedPRs":13841,"stars":48667},{"closedIssues":11573,"openIssues":367,"stars":48665,"openPRs":209,"closedPRs":2678,"mergedPRs":13841,"timestamp":1610864504},{"openIssues":367,"mergedPRs":13841,"openPRs":209,"closedPRs":2678,"closedIssues":11573,"timestamp":1610861491,"stars":48664},{"closedIssues":11573,"closedPRs":2678,"mergedPRs":13841,"openIssues":366,"timestamp":1610857429,"openPRs":209,"stars":48662},{"stars":48662,"mergedPRs":13841,"closedIssues":11573,"timestamp":1610855099,"openIssues":366,"openPRs":209,"closedPRs":2678},{"mergedPRs":13841,"closedPRs":2678,"openPRs":209,"stars":48662,"openIssues":366,"closedIssues":11573,"timestamp":1610850645},{"closedIssues":11573,"openPRs":209,"mergedPRs":13841,"openIssues":366,"closedPRs":2678,"timestamp":1610843093,"stars":48662},{"mergedPRs":13841,"stars":48662,"openIssues":366,"timestamp":1610839337,"closedPRs":2678,"openPRs":209,"closedIssues":11572},{"openPRs":209,"mergedPRs":13841,"closedPRs":2678,"timestamp":1610835115,"closedIssues":11572,"openIssues":366,"stars":48660},{"mergedPRs":13841,"openPRs":209,"closedPRs":2678,"closedIssues":11571,"stars":48659,"openIssues":367,"timestamp":1610831615},{"mergedPRs":13841,"openIssues":367,"timestamp":1610828457,"closedPRs":2678,"stars":48659,"closedIssues":11571,"openPRs":209},{"openIssues":367,"closedPRs":2678,"timestamp":1610825754,"mergedPRs":13841,"closedIssues":11571,"openPRs":209,"stars":48661},{"mergedPRs":13841,"openIssues":367,"timestamp":1610820386,"openPRs":209,"stars":48662,"closedIssues":11571,"closedPRs":2678},{"openPRs":209,"openIssues":367,"timestamp":1610813815,"closedIssues":11571,"closedPRs":2678,"mergedPRs":13841,"stars":48661},{"openIssues":367,"openPRs":209,"closedPRs":2678,"closedIssues":11571,"mergedPRs":13841,"timestamp":1610809907,"stars":48661},{"closedPRs":2678,"closedIssues":11571,"mergedPRs":13841,"timestamp":1610806874,"stars":48660,"openPRs":209,"openIssues":367},{"openPRs":209,"closedPRs":2678,"openIssues":367,"timestamp":1610804016,"mergedPRs":13841,"closedIssues":11571,"stars":48660},{"closedIssues":11570,"openPRs":209,"openIssues":368,"timestamp":1610799295,"closedPRs":2678,"stars":48659,"mergedPRs":13841},{"stars":48658,"timestamp":1610796452,"mergedPRs":13841,"openPRs":209,"closedIssues":11570,"closedPRs":2678,"openIssues":368},{"openPRs":211,"closedIssues":11570,"openIssues":368,"timestamp":1610792928,"mergedPRs":13839,"closedPRs":2678,"stars":48657},{"mergedPRs":13838,"closedIssues":11569,"openIssues":369,"timestamp":1610789257,"openPRs":210,"stars":48657,"closedPRs":2678},{"closedIssues":11569,"closedPRs":2678,"timestamp":1610785256,"openPRs":210,"stars":48657,"openIssues":369,"mergedPRs":13838},{"openPRs":210,"stars":48657,"timestamp":1610782067,"openIssues":369,"closedIssues":11569,"closedPRs":2678,"mergedPRs":13838},{"timestamp":1610778144,"closedIssues":11569,"openIssues":369,"openPRs":210,"mergedPRs":13838,"closedPRs":2678,"stars":48657},{"openPRs":210,"closedPRs":2678,"openIssues":369,"mergedPRs":13838,"stars":48657,"timestamp":1610775050,"closedIssues":11569},{"openPRs":210,"closedPRs":2678,"mergedPRs":13838,"stars":48657,"openIssues":369,"timestamp":1610770893,"closedIssues":11569},{"timestamp":1610768677,"closedIssues":11569,"openPRs":210,"openIssues":369,"mergedPRs":13838,"stars":48657,"closedPRs":2678},{"closedPRs":2678,"stars":48657,"openIssues":368,"timestamp":1610764256,"closedIssues":11569,"openPRs":210,"mergedPRs":13838},{"openPRs":210,"closedIssues":11568,"closedPRs":2678,"stars":48657,"openIssues":368,"mergedPRs":13838,"timestamp":1610756984},{"openIssues":367,"closedIssues":11568,"closedPRs":2678,"mergedPRs":13838,"timestamp":1610753181,"stars":48657,"openPRs":210},{"openPRs":210,"stars":48657,"timestamp":1610748924,"mergedPRs":13838,"closedIssues":11568,"openIssues":367,"closedPRs":2678},{"closedPRs":2678,"openPRs":210,"closedIssues":11568,"mergedPRs":13838,"stars":48655,"openIssues":367,"timestamp":1610745479},{"timestamp":1610742232,"closedIssues":11568,"stars":48655,"openPRs":210,"mergedPRs":13838,"openIssues":366,"closedPRs":2678},{"mergedPRs":13838,"stars":48655,"openIssues":367,"openPRs":210,"closedIssues":11567,"timestamp":1610739504,"closedPRs":2678},{"openPRs":210,"openIssues":367,"closedPRs":2678,"mergedPRs":13837,"closedIssues":11567,"timestamp":1610734148,"stars":48652},{"closedIssues":11566,"openPRs":210,"timestamp":1610727546,"closedPRs":2678,"mergedPRs":13837,"stars":48651,"openIssues":368},{"openIssues":368,"openPRs":209,"closedPRs":2678,"stars":48651,"closedIssues":11566,"mergedPRs":13837,"timestamp":1610723628},{"closedIssues":11565,"closedPRs":2678,"openPRs":211,"mergedPRs":13835,"openIssues":369,"stars":48651,"timestamp":1610720590},{"timestamp":1610717713,"openIssues":367,"closedIssues":11565,"mergedPRs":13834,"closedPRs":2678,"openPRs":212,"stars":48650},{"openPRs":212,"timestamp":1610712953,"mergedPRs":13833,"closedIssues":11562,"closedPRs":2678,"openIssues":369,"stars":48650},{"closedPRs":2678,"closedIssues":11562,"mergedPRs":13833,"stars":48649,"timestamp":1610710128,"openPRs":212,"openIssues":368},{"mergedPRs":13833,"openPRs":211,"closedPRs":2678,"stars":48649,"openIssues":367,"closedIssues":11563,"timestamp":1610706598},{"timestamp":1610702911,"closedPRs":2676,"mergedPRs":13833,"closedIssues":11563,"stars":48649,"openPRs":212,"openIssues":367},{"mergedPRs":13832,"closedPRs":2675,"timestamp":1610698823,"openIssues":369,"closedIssues":11561,"stars":48651,"openPRs":214},{"openIssues":369,"mergedPRs":13832,"closedIssues":11561,"timestamp":1610695620,"stars":48651,"openPRs":214,"closedPRs":2675},{"stars":48650,"mergedPRs":13832,"timestamp":1610691660,"openPRs":214,"openIssues":369,"closedIssues":11561,"closedPRs":2675},{"closedIssues":11560,"mergedPRs":13832,"stars":48650,"openPRs":214,"closedPRs":2675,"timestamp":1610688589,"openIssues":370},{"mergedPRs":13832,"closedPRs":2675,"openIssues":370,"openPRs":214,"closedIssues":11560,"timestamp":1610684482,"stars":48650},{"openIssues":370,"closedIssues":11560,"mergedPRs":13832,"stars":48650,"timestamp":1610682123,"openPRs":214,"closedPRs":2675},{"timestamp":1610677654,"openPRs":214,"mergedPRs":13832,"openIssues":370,"closedIssues":11560,"stars":48649,"closedPRs":2675},{"mergedPRs":13831,"closedPRs":2675,"stars":48649,"timestamp":1610670384,"openPRs":215,"closedIssues":11560,"openIssues":369},{"openPRs":215,"closedIssues":11560,"stars":48647,"openIssues":369,"closedPRs":2675,"timestamp":1610666584,"mergedPRs":13831},{"closedIssues":11560,"timestamp":1610662330,"mergedPRs":13831,"stars":48647,"openIssues":369,"openPRs":215,"closedPRs":2675},{"openPRs":215,"closedPRs":2675,"stars":48647,"closedIssues":11560,"timestamp":1610658895,"mergedPRs":13831,"openIssues":369},{"timestamp":1610655823,"mergedPRs":13831,"stars":48647,"closedIssues":11560,"openIssues":369,"openPRs":214,"closedPRs":2675},{"closedIssues":11560,"stars":48647,"openPRs":214,"closedPRs":2675,"mergedPRs":13831,"timestamp":1610653221,"openIssues":369},{"mergedPRs":13831,"timestamp":1610647819,"stars":48645,"closedPRs":2674,"closedIssues":11560,"openIssues":369,"openPRs":214},{"timestamp":1610641128,"mergedPRs":13830,"closedPRs":2674,"openPRs":214,"openIssues":370,"closedIssues":11559,"stars":48644},{"stars":48641,"mergedPRs":13829,"timestamp":1610637246,"closedIssues":11559,"openIssues":370,"closedPRs":2673,"openPRs":215},{"timestamp":1610634217,"openPRs":216,"stars":48640,"mergedPRs":13828,"openIssues":370,"closedPRs":2673,"closedIssues":11559},{"timestamp":1610631329,"mergedPRs":13827,"closedPRs":2673,"openPRs":216,"closedIssues":11559,"stars":48640,"openIssues":370},{"mergedPRs":13824,"stars":48640,"closedPRs":2673,"openIssues":371,"openPRs":218,"closedIssues":11558,"timestamp":1610626578},{"timestamp":1610623769,"stars":48639,"closedPRs":2673,"closedIssues":11557,"mergedPRs":13823,"openIssues":372,"openPRs":218},{"timestamp":1610620245,"stars":48639,"openPRs":217,"closedIssues":11557,"mergedPRs":13823,"closedPRs":2673,"openIssues":372},{"timestamp":1610616575,"closedIssues":11554,"mergedPRs":13823,"openPRs":217,"stars":48639,"openIssues":375,"closedPRs":2673},{"stars":48640,"closedPRs":2673,"mergedPRs":13822,"closedIssues":11547,"openPRs":218,"timestamp":1610612699,"openIssues":382},{"stars":48640,"closedIssues":11547,"mergedPRs":13822,"openPRs":218,"openIssues":382,"closedPRs":2673,"timestamp":1610609375},{"closedIssues":11547,"mergedPRs":13822,"openIssues":381,"closedPRs":2673,"timestamp":1610605446,"openPRs":218,"stars":48639},{"openIssues":381,"closedPRs":2673,"stars":48639,"timestamp":1610602327,"openPRs":218,"closedIssues":11547,"mergedPRs":13822},{"stars":48641,"closedPRs":2673,"openPRs":218,"closedIssues":11547,"mergedPRs":13822,"openIssues":381,"timestamp":1610598245},{"stars":48641,"closedIssues":11547,"timestamp":1610595966,"mergedPRs":13822,"openIssues":381,"openPRs":218,"closedPRs":2673},{"openIssues":381,"closedIssues":11547,"stars":48641,"closedPRs":2673,"openPRs":218,"timestamp":1610591504,"mergedPRs":13822},{"closedPRs":2672,"timestamp":1610584281,"stars":48639,"closedIssues":11547,"mergedPRs":13821,"openPRs":218,"openIssues":379},{"closedPRs":2672,"openIssues":379,"stars":48639,"openPRs":217,"mergedPRs":13819,"timestamp":1610580311,"closedIssues":11546},{"openPRs":217,"closedPRs":2672,"stars":48637,"openIssues":379,"mergedPRs":13819,"closedIssues":11546,"timestamp":1610576023},{"timestamp":1610572480,"mergedPRs":13819,"openIssues":379,"closedPRs":2672,"stars":48635,"openPRs":216,"closedIssues":11546},{"closedIssues":11546,"stars":48633,"mergedPRs":13819,"timestamp":1610569174,"closedPRs":2672,"openPRs":215,"openIssues":378},{"closedIssues":11546,"openIssues":378,"openPRs":215,"stars":48633,"timestamp":1610566870,"closedPRs":2672,"mergedPRs":13819},{"closedPRs":2672,"openIssues":378,"stars":48633,"closedIssues":11546,"mergedPRs":13819,"timestamp":1610561511,"openPRs":215},{"closedPRs":2672,"mergedPRs":13818,"openPRs":216,"timestamp":1610554700,"stars":48633,"openIssues":376,"closedIssues":11546},{"openPRs":216,"timestamp":1610550852,"closedPRs":2672,"mergedPRs":13818,"stars":48633,"closedIssues":11546,"openIssues":375},{"openIssues":375,"openPRs":216,"closedIssues":11546,"mergedPRs":13818,"timestamp":1610547772,"stars":48632,"closedPRs":2672},{"timestamp":1610544867,"closedIssues":11546,"openPRs":216,"stars":48631,"closedPRs":2672,"mergedPRs":13818,"openIssues":375},{"closedIssues":11546,"closedPRs":2672,"mergedPRs":13817,"timestamp":1610540110,"openPRs":217,"stars":48630,"openIssues":375},{"mergedPRs":13817,"openIssues":375,"closedPRs":2672,"timestamp":1610537253,"openPRs":217,"closedIssues":11546,"stars":48630},{"openPRs":216,"openIssues":375,"timestamp":1610533749,"mergedPRs":13817,"stars":48630,"closedIssues":11546,"closedPRs":2672},{"closedIssues":11543,"timestamp":1610530119,"stars":48628,"openIssues":378,"openPRs":221,"closedPRs":2671,"mergedPRs":13812},{"closedPRs":2671,"timestamp":1610526106,"openIssues":378,"closedIssues":11543,"mergedPRs":13812,"openPRs":221,"stars":48625},{"mergedPRs":13811,"stars":48625,"closedIssues":11543,"timestamp":1610522703,"openPRs":222,"closedPRs":2671,"openIssues":378},{"closedPRs":2671,"openIssues":378,"closedIssues":11543,"mergedPRs":13811,"openPRs":222,"timestamp":1610518815,"stars":48624},{"timestamp":1610515757,"closedIssues":11543,"mergedPRs":13811,"closedPRs":2671,"stars":48623,"openIssues":378,"openPRs":222},{"openPRs":222,"closedPRs":2671,"openIssues":378,"stars":48623,"closedIssues":11543,"mergedPRs":13811,"timestamp":1610511778},{"mergedPRs":13811,"openIssues":377,"timestamp":1610508924,"closedPRs":2671,"closedIssues":11543,"openPRs":222,"stars":48623},{"mergedPRs":13811,"stars":48623,"closedIssues":11543,"openIssues":376,"timestamp":1610504541,"openPRs":222,"closedPRs":2671},{"timestamp":1610497348,"openIssues":376,"openPRs":222,"mergedPRs":13811,"closedIssues":11543,"stars":48621,"closedPRs":2671},{"openPRs":222,"closedPRs":2671,"mergedPRs":13811,"closedIssues":11543,"stars":48621,"openIssues":376,"timestamp":1610493580},{"timestamp":1610489353,"openIssues":376,"openPRs":222,"closedIssues":11543,"closedPRs":2671,"stars":48622,"mergedPRs":13811},{"stars":48622,"closedPRs":2671,"openIssues":376,"openPRs":222,"mergedPRs":13811,"closedIssues":11543,"timestamp":1610485720},{"closedIssues":11543,"stars":48622,"closedPRs":2671,"openIssues":376,"timestamp":1610482607,"openPRs":222,"mergedPRs":13811},{"closedPRs":2671,"mergedPRs":13811,"closedIssues":11543,"openPRs":222,"stars":48622,"timestamp":1610479931,"openIssues":376},{"stars":48624,"mergedPRs":13811,"openIssues":376,"closedPRs":2671,"openPRs":221,"closedIssues":11543,"timestamp":1610474348},{"timestamp":1610467877,"openPRs":220,"mergedPRs":13809,"stars":48623,"openIssues":376,"closedPRs":2671,"closedIssues":11543},{"openIssues":376,"openPRs":220,"closedPRs":2671,"timestamp":1610463949,"mergedPRs":13809,"closedIssues":11543,"stars":48621},{"closedIssues":11542,"closedPRs":2671,"openIssues":377,"timestamp":1610460814,"openPRs":220,"mergedPRs":13809,"stars":48620},{"openPRs":221,"openIssues":376,"closedPRs":2671,"timestamp":1610457965,"closedIssues":11542,"mergedPRs":13808,"stars":48619},{"openIssues":378,"stars":48619,"timestamp":1610453188,"mergedPRs":13808,"closedPRs":2671,"closedIssues":11540,"openPRs":219},{"closedIssues":11539,"mergedPRs":13807,"openIssues":379,"stars":48619,"closedPRs":2671,"openPRs":220,"timestamp":1610450326},{"closedIssues":11539,"closedPRs":2671,"mergedPRs":13807,"openIssues":379,"timestamp":1610446822,"openPRs":219,"stars":48619},{"timestamp":1610443195,"stars":48619,"closedIssues":11537,"closedPRs":2671,"mergedPRs":13804,"openIssues":381,"openPRs":217},{"openPRs":219,"timestamp":1610439278,"closedIssues":11537,"closedPRs":2669,"stars":48619,"openIssues":381,"mergedPRs":13804},{"timestamp":1610436006,"mergedPRs":13804,"openIssues":381,"openPRs":219,"closedIssues":11537,"stars":48619,"closedPRs":2669},{"mergedPRs":13804,"closedIssues":11537,"closedPRs":2669,"timestamp":1610432114,"openIssues":381,"openPRs":219,"stars":48618},{"timestamp":1610429150,"stars":48617,"openIssues":382,"mergedPRs":13803,"openPRs":220,"closedIssues":11536,"closedPRs":2669},{"openPRs":220,"closedPRs":2669,"openIssues":382,"timestamp":1610425290,"stars":48617,"mergedPRs":13803,"closedIssues":11536},{"mergedPRs":13803,"openPRs":220,"closedPRs":2669,"openIssues":382,"stars":48616,"closedIssues":11536,"timestamp":1610422110},{"timestamp":1610417797,"openPRs":220,"closedPRs":2669,"stars":48615,"closedIssues":11536,"openIssues":382,"mergedPRs":13803},{"closedIssues":11536,"closedPRs":2669,"openPRs":220,"stars":48612,"openIssues":381,"mergedPRs":13803,"timestamp":1610410537},{"openPRs":220,"stars":48613,"timestamp":1610406915,"mergedPRs":13803,"closedIssues":11536,"closedPRs":2669,"openIssues":381},{"closedIssues":11536,"closedPRs":2669,"stars":48613,"mergedPRs":13803,"openIssues":381,"openPRs":220,"timestamp":1610402858},{"closedPRs":2669,"mergedPRs":13802,"stars":48613,"closedIssues":11536,"openPRs":221,"openIssues":381,"timestamp":1610399064},{"openIssues":381,"closedIssues":11536,"timestamp":1610395774,"stars":48612,"openPRs":221,"closedPRs":2669,"mergedPRs":13802},{"closedIssues":11536,"closedPRs":2669,"openIssues":381,"mergedPRs":13801,"openPRs":222,"stars":48612,"timestamp":1610393166},{"stars":48610,"closedPRs":2669,"mergedPRs":13801,"timestamp":1610387577,"openPRs":219,"closedIssues":11536,"openIssues":381},{"closedPRs":2669,"openIssues":381,"openPRs":220,"mergedPRs":13800,"closedIssues":11536,"stars":48609,"timestamp":1610381376},{"closedPRs":2669,"openPRs":219,"closedIssues":11536,"stars":48608,"openIssues":380,"mergedPRs":13800,"timestamp":1610377666},{"openPRs":216,"closedIssues":11536,"closedPRs":2669,"stars":48608,"mergedPRs":13800,"openIssues":380,"timestamp":1610374306},{"closedPRs":2669,"closedIssues":11536,"timestamp":1610371499,"stars":48607,"openIssues":380,"mergedPRs":13798,"openPRs":217},{"timestamp":1610366682,"stars":48606,"mergedPRs":13797,"openPRs":218,"openIssues":381,"closedIssues":11534,"closedPRs":2669},{"timestamp":1610363866,"stars":48605,"closedPRs":2669,"openIssues":381,"mergedPRs":13797,"openPRs":217,"closedIssues":11534},{"closedIssues":11530,"stars":48604,"openIssues":385,"timestamp":1610360392,"openPRs":220,"mergedPRs":13793,"closedPRs":2669},{"closedPRs":2667,"stars":48604,"openIssues":387,"timestamp":1610356807,"closedIssues":11528,"mergedPRs":13788,"openPRs":227},{"openIssues":387,"timestamp":1610352747,"closedPRs":2667,"stars":48604,"openPRs":237,"closedIssues":11528,"mergedPRs":13778},{"openPRs":237,"mergedPRs":13778,"stars":48603,"closedPRs":2667,"timestamp":1610349508,"closedIssues":11528,"openIssues":387},{"timestamp":1610345623,"stars":48603,"openPRs":237,"closedPRs":2667,"mergedPRs":13778,"closedIssues":11528,"openIssues":387},{"timestamp":1610342728,"closedIssues":11528,"openIssues":387,"openPRs":237,"closedPRs":2667,"mergedPRs":13778,"stars":48603},{"timestamp":1610338959,"closedPRs":2667,"mergedPRs":13778,"openPRs":237,"stars":48602,"closedIssues":11528,"openIssues":386},{"timestamp":1610335519,"closedIssues":11528,"openIssues":386,"mergedPRs":13778,"closedPRs":2667,"openPRs":237,"stars":48600},{"mergedPRs":13778,"closedPRs":2667,"stars":48598,"openPRs":236,"timestamp":1610331237,"closedIssues":11528,"openIssues":386},{"mergedPRs":13778,"timestamp":1610323908,"closedIssues":11528,"openPRs":227,"stars":48594,"openIssues":386,"closedPRs":2667},{"mergedPRs":13778,"openPRs":227,"closedPRs":2667,"timestamp":1610320440,"closedIssues":11528,"openIssues":386,"stars":48593},{"openPRs":227,"timestamp":1610316369,"openIssues":386,"mergedPRs":13778,"closedIssues":11528,"closedPRs":2667,"stars":48593},{"closedPRs":2667,"closedIssues":11528,"mergedPRs":13778,"openPRs":227,"timestamp":1610312485,"openIssues":386,"stars":48592},{"closedPRs":2667,"timestamp":1610309224,"openIssues":386,"closedIssues":11528,"openPRs":227,"mergedPRs":13778,"stars":48592},{"timestamp":1610306687,"stars":48592,"openPRs":227,"mergedPRs":13778,"closedIssues":11528,"closedPRs":2667,"openIssues":385},{"timestamp":1610301168,"closedPRs":2667,"openIssues":385,"openPRs":227,"closedIssues":11528,"stars":48592,"mergedPRs":13778},{"timestamp":1610295110,"closedIssues":11528,"mergedPRs":13778,"openIssues":384,"closedPRs":2667,"stars":48592,"openPRs":227},{"mergedPRs":13778,"openIssues":384,"stars":48592,"timestamp":1610290910,"closedPRs":2667,"openPRs":226,"closedIssues":11528},{"openPRs":226,"stars":48592,"timestamp":1610287668,"mergedPRs":13778,"closedPRs":2667,"openIssues":384,"closedIssues":11528},{"openIssues":384,"closedIssues":11528,"mergedPRs":13778,"timestamp":1610284790,"closedPRs":2667,"stars":48591,"openPRs":226},{"mergedPRs":13778,"closedPRs":2667,"stars":48592,"openPRs":226,"openIssues":384,"timestamp":1610280123,"closedIssues":11528},{"closedPRs":2667,"stars":48592,"openIssues":384,"mergedPRs":13778,"timestamp":1610277179,"closedIssues":11528,"openPRs":226},{"closedPRs":2667,"timestamp":1610273720,"openPRs":225,"stars":48590,"openIssues":384,"closedIssues":11528,"mergedPRs":13778},{"timestamp":1610270100,"openIssues":385,"mergedPRs":13778,"closedIssues":11527,"closedPRs":2667,"openPRs":225,"stars":48592},{"openPRs":225,"closedIssues":11527,"closedPRs":2667,"mergedPRs":13778,"timestamp":1610266282,"stars":48592,"openIssues":385},{"timestamp":1610263023,"openPRs":225,"closedIssues":11527,"openIssues":385,"mergedPRs":13778,"stars":48592,"closedPRs":2667},{"timestamp":1610259144,"openIssues":385,"closedPRs":2667,"mergedPRs":13778,"closedIssues":11527,"openPRs":225,"stars":48590},{"mergedPRs":13778,"timestamp":1610256257,"openIssues":385,"openPRs":225,"closedPRs":2667,"closedIssues":11527,"stars":48589},{"closedIssues":11527,"openIssues":385,"timestamp":1610252518,"stars":48589,"closedPRs":2667,"mergedPRs":13778,"openPRs":225}]
